Workbook

Sheet 01_README
A1: СТРОЙИНТЕЛЛЕКТ.СМЕТЧИК v8.2 · ИИ-СМЕТЧИК · СМЕТНЫЙ РАЗБОР
A2: ЖДПП «Зауралье» — СОТ+ЭОМ · ст. Зауралье, 76 км · Половинский р-н · Курганская обл. · SI-2026-KRG-ZAU-СОТ · 03.08.2026
A4: ЗАКЛЮЧЕНИЕ СМЕТЧИКА — 4 СТРОКИ
A5: 🔴 НМЦК НЕДОСТОВЕРНА — НЕ ПОДАВАТЬ БЕЗ ОТВЕТА РЖД. Блок «вынос/возврат контактной сети» 64 710 398 ₽ (198,12 км) проектом РД не обоснован (ГНБ-проколы, опоры ≥2 м от КС). Согласна с ИИ-ГИП — ВОР по блоку возвращаю. Это 62% Гл.1-9 без НДС.
A6: 🔴 ДВОЙНОЙ СЧЁТ ПНР — 890 669,50 ₽. ПНР сидит и внутри ЛСР СОТ, и отдельным ЛСР в Гл.9. В НМЦК задвоено ≈1,09 млн ₽ с НДС. «Копейка в копейку» у ИИ-руководителя проекта сошлась именно из-за задвоения. Урок Каранайаула наоборот — не выпало, а задвоилось.
A7: 🔴 ОБОРУДОВАНИЕ СОТ НЕ В СМЕТЕ. 202 камеры, 2×СХД, 8×РЛС, 8×НЕО, 36 коммутаторов, ИБП как поставка отсутствуют (в смете 2,22 млн = монтаж + криптошлюзы ViPNet 1,39 млн). Материалы 1,86 млн — аномально мало. Объём не определён → себес неполон.
A8: 🟡 НДС 20% в смете, с 01.01.2026 — 22% (ФЗ 425-ФЗ), работы 2026 → недобор ≈2,14 млн ₽ при твёрдой цене. Смета в ценах II кв.2025, исполнение 2026 → нужен пересчёт индексов (флаг 7). Обе правки — до подписания.
A10: КЛЮЧЕВЫЕ ЦИФРЫ (рубли)
A11: Показатель | B11: Сумма, ₽ | C11: Комментарий
A12: Сметная стоимость по ССРСС, с НДС 20% | B12: =04_Свод_ЛСР!C29 -> 1.2849148e+08 | C12: сумма 4 ЛСР ×1,02 ×1,20; ССРСС стр.49
A13: в т.ч. Гл.1-9 (= сумма 4 ЛСР) | B13: =04_Свод_ЛСР!C25 -> 1.049767e+08 | C13: сходится до рубля
A14: ❗ Блок «вынос КС» — НЕ обоснован РД | B14: =05_Блок_КС!F15 -> 64710398 | C14: 198,12 км · воздух/незакрываемо при КС-2
A15: ❗ Двойной счёт ПНР (без НДС) | B15: =04_Свод_ЛСР!C20 -> 890669.5 | C15: задвоен: ЛСР СОТ + отдельный ЛСР ПНР
A16: ❗ Недобор НДС 20%→22% (тверд.цена) | B16: =08_Пересчёт_2026!B15 -> 2141524.7 | C16: ФЗ 425-ФЗ, работы 2026
A17: Материалы в смете (аномально мало) | B17: 1862206.2 | C17: 1,86 млн на весь объект
A18: Оборудование в смете (без «железа» ПД) | B18: 2222036.3 | C18: нет камер/серверов/РЛС/ИБП
A19: Номинальный запас НР+СП («жирок») | B19: =07_НР_СП!B7 -> 40471970 | C19: из них ≈24 млн — на блоке КС
A21: КАРТА ФАЙЛА
A22: Лист | B22: Содержание
A23: 02_Объект | B23: Паспорт объекта (ИИ-руководитель проекта + ИИ-ГИП)
A24: 03_Чеклист_ЛСР | B24: Чеклист полноты ЛСР — протокол v8 (5 пунктов)
A25: 04_Свод_ЛСР ⭐ | B25: 4 ЛСР vs Гл.1-9: сходимость и двойной счёт ПНР
A26: 05_Блок_КС ⭐⭐ | B26: Контактная сеть 198 км — разбор по позициям в ₽
A27: 06_Матер_Оборуд | B27: Смета vs спецификация ПД — чего не хватает
A28: 07_НР_СП | B28: Разложение НР/СП — где висит «жирок»
A29: 08_Пересчёт_2026 | B29: Индексы II кв.2025 → 2026 + НДС 22%
A30: 09_Конъюнктура | B30: Рыночные ориентиры: СИП-4, опоры, плиты, ВОК
A31: 10_Финрезультат ⭐ | B31: Влияние на маржу — 3 сценария по блоку КС
A32: 11_Передачи смежникам | B32: Задания команде + алерт ИИ-руководителю проекта
A34: ЦВЕТ: 🟨 редактируемые ячейки (индекс/цены/сценарий) · 🟥 риск/убыток · 🟩 обосновано · синий текст — исходные данные ЛСР · чёрный — формулы. Точность: смета с ЛСР ±3-5%; рыночные ориентиры ±15%.

Sheet 02_Объект
A1: ПАСПОРТ ОБЪЕКТА
A2: Источник: паспорт ИИ-руководителя проекта (Такт 0) + техзаключение ИИ-ГИП (ЦИМ, Такт 1)
A4: Параметр | B4: Значение
A5: ID объекта | B5: SI-2026-KRG-ZAU-СОТ
A6: Наименование | B6: Оснащение системой видеонаблюдения ЖДПП «Зауралье». СОТ (охранное ТВ) + ЭОМ (электроснабжение). Актуализация ПСД
A7: Адрес | B7: Курганская обл., Половинский р-н, ст. Зауралье, 76 км, пк 6+80 — пограничный ж/д пункт пропуска
A8: Заказчик | B8: ⚠ НЕ идентифицирован. Интересант — ПУ ФСБ по Курганской и Тюменской обл. Установить ЛПР и финансирование (ИИ-договорник)
A9: Проектировщик | B9: АО «Оргэнергострой», Москва. Проект 1102/23-Зауралье. ГИП Безъязыков Д.С.
A10: Смету составил | B10: инж. Распопов Н.А.; проверил Гончаров К.В.
A11: Тип объекта | B11: Слаботочка (СОТ) + электроснабжение 0,4 кВ (ЭОМ) на действующей ж/д станции. НЕ капстрой — монтаж систем
A12: Особый режим | B12: Погранпункт → категорированные помещения (ФЗ 5485-1, спецпроверки ФСБ). Контактная сеть 27,5 кВ → «окна» РЖД
A13: Стадия | B13: Предстартовая проработка. ПД «П». РД для точных объёмов ещё нужна
A14: Сметная стоимость | B14: 128 491,5 тыс.₽ с НДС 20% (текущий уровень цен II кв.2025); без НДС 107 076,24 тыс.₽
A15: Метод | B15: Ресурсный + ресурсно-индексный. ГРАНД-Смета 2026.1, ФСНБ (421/пр) + индексы до 299/пр от 19.05.2025
... A19: Заключение РП | B19: 🟡 ЖЁЛТЫЙ — брать в проработку, себес пока НЕ достоверен (ИИ-руководитель проекта)

Sheet 03_Чеклист_ЛСР
A1: ЧЕКЛИСТ ПОЛНОТЫ ЛСР — ПРОТОКОЛ v8 (5 ПУНКТОВ)
A2: Результат: 2 из 5 пройдено (с оговорками) — объект НЕ готов к подаче без эскалации
A4: № | B4: Пункт проверки | C4: Статус | D4: Комментарий
A5: 1 | B5: Сумма ЛСР = Свод по главам? | C5: 🟡 ФОРМАЛЬНО | D5: Сумма 4 ЛСР = 104 976 702 ₽ = Гл.1-9 до рубля. НО сходимость обеспечена ЗАДВОЕНИЕМ ПНР (п.2). По существу завышено на 890 670 ₽.
A6: 2 | B6: Нет дублей между ЛСР? | C6: ❌ НЕ ПРОЙДЕНО | D6: ПНР 890 669,50 ₽ задвоен: внутри ЛСР СОТ + отдельный ЛСР в Гл.9. Двойной счёт. Лист 04.
A7: 3 | B7: Нет отриц./нулевых объёмов? | C7: 🟡 ЧАСТИЧНО | D7: «Расчётный ток 95,28 А» — ошибка метода (ИИ-ГИП), на смету не влияет. Технич. нулей не выявлено.
A8: 4 | B8: Все ЛСР в маппинге (нет белых пятен)? | C8: ❌ НЕ ПРОЙДЕНО | D8: Оборудование СОТ (202 камеры, 2×СХД, 8×РЛС, 36 коммут., ИБП) как поставка ОТСУТСТВУЕТ. Материалы 1,86 млн. Лист 06.
A9: 5 | B9: Крупный блок ≥5% НМЦК обоснован? | C9: ❌ НЕ ПРОЙДЕНО | D9: Блок «вынос КС» 64 710 398 ₽ (62% Гл.1-9) не обоснован РД. Блокер. Запрос в РЖД через ИИ-договорника. Лист 05.
A11: ИТОГ: 2 из 5. Объект не готов к подаче без эскалации 3 красных пунктов. Финальное решение — за ИИ-руководителем проекта.

Sheet 04_Свод_ЛСР
A1: СВОД 4 ЛСР vs Гл.1-9 — СХОДИМОСТЬ И ДВОЙНОЙ СЧЁТ ПНР
A2: Источник: ВСЕГО по смете каждого ЛСР
A4: А. ИТОГИ ЧЕТЫРЁХ ЛСР
A5: ЛСР | B5: Шифр | C5: ВСЕГО, ₽ | D5: Что внутри
A6: СОТ — Система видеонаблюдения | B6: 05-02 | C6: 14198885 | D6: монтаж 11 086 179 + оборуд 2 222 036 + ПНР 890 670 ⚠
A7: ЭОМ — Система электроснабжения | B7: 05-01 | C7: 89532565 | D7: строит 20 096 173 + монтаж 69 436 392 (в т.ч. блок КС)
A8: ПНР — Пусконаладка СОТ | B8: 09-01 | C8: 890669.5 | D8: ⚠ дубль: та же ПНР, что внутри ЛСР СОТ
A9: СП и СИ — спецпроверки ФСБ | B9: 09-02 | C9: 354583.33 | D9: категорированные помещения, ФЗ 5485-1
A10: СУММА 4 ЛСР | C10: =SUM(C6:C9) -> 1.049767e+08 | D10: ≈ Гл.1-9 ССРСС — сходится до рубля
A12: Б. ГДЕ СИДИТ ПНР (раскрытие ЛСР СОТ)
A13: Компонент ЛСР СОТ | C13: ₽ | D13: Примечание
A14: Монтажные работы | C14: 11086179 | D14: монтаж камер, СКС, ВОЛС
A15: Оборудование | C15: 2222036.3 | D15: в т.ч. криптошлюзы ViPNet 1 386 845 («отсутств. в ФРСН»)
A16: Пусконаладочные работы (ПНР) | C16: 890669.5 | D16: ⚠ ЭТА ЖЕ ПНР дублирована отдельным ЛСР в Гл.9
A17: ВСЕГО ЛСР СОТ | C17: =SUM(C14:C16) -> 14198885 | D17: итого 14 198 885 ₽
A19: В. ДВОЙНОЙ СЧЁТ ПНР — ДЕНЕЖНЫЙ ЭФФЕКТ
A20: Двойной счёт ПНР (без НДС) | C20: 890669.5 | D20: строка «ПНР» в ЛСР СОТ = отдельный ЛСР ПНР, рубль в рубль
A21: с непредв. 2% и НДС 20% | C21: =C20*1.02*1.2 -> 1090179.5 | D21: завышение НМЦК с НДС ≈ 1,09 млн ₽
A23: Г. ПЕРЕХОД К НМЦК (ССРСС)
A24: Строка ССРСС | C24: ₽ | D24: Примечание
A25: Гл.1-9 (= сумма 4 ЛСР) | C25: =C10 -> 1.049767e+08 | D25: сумма 4 ЛСР
A26: Непредвиденные 2% (421/пр п.179) | C26: =C25*0.02 -> 2099534 | D26: 2% непроизв. объект
A27: Итого без НДС | C27: =C25+C26 -> 1.0707624e+08
A28: НДС 20% (в смете; должно 22%) | C28: =C27*0.2 -> 21415247 | D28: ⚠ ФЗ 425-ФЗ
A29: ВСЕГО по ССРСС с НДС 20% | C29: =C27+C28 -> 1.2849148e+08 | D29: итого 128 491 484 ₽

Sheet 05_Блок_КС
A1: БЛОК «ВЫНОС/ВОЗВРАТ КОНТАКТНОЙ СЕТИ» (ГЭСНм20-03-035) — РАЗБОР В РУБЛЯХ
A2: Источник: ЛСР ЭОМ, Раздел 2. Позиции — «Всего по позиции» (прямые+НР+СП). Заключение ИИ-ГИП: 🔴 ВОЗВРАЩАЮ
A4: Проектное решение РД: пересечения КС решены проколами ГНБ на 3 м, опоры ≥2 м от КС (ТУ РЖД пп.5-6). Значит вынос/возврат КС обоснован ТОЛЬКО в 3 местах жёстких поперечин П-перехода. Большой блок 198 км физически невозможен на станции 2,5 км (кратность к физике ~11×).
A6: ❌ БОЛЬШОЙ БЛОК — НЕ ОБОСНОВАН РД (воздух / незакрываемо при КС-2)
A7: Поз. | B7: Расценка ГЭСНм | C7: Ед. | D7: Объём | F7: ВСЕГО по позиции, ₽
A8: 61 | B8: ГЭСНм20-035-01 | C8: км | D8: 15.24 | F8: 21383323
A9: 62 | B9: ГЭСНм20-035-02 | C9: км | D9: 30.48 | F9: 12215273
A10: 63 | B10: ГЭСНм20-035-04 | C10: км | D10: 15.24 | F10: 1403436.2
A11: 64 | B11: ГЭСНм20-035-03 | C11: км | D11: 45.72 | F11: 9910041.2
A12: 65 | B12: ГЭСНм20-035-05 | C12: км | D12: 15.24 | F12: 3282293.7
A13: 66 | B13: ГЭСНм20-035-06 | C13: км | D13: 15.24 | F13: 3302643
A14: 67 | B14: ГЭСНм20-035-03 | C14: км | D14: 60.96 | F14: 13213388
A15: ИТОГО большой блок | D15: =SUM(D8:D14) -> 198.12 | E15: км | F15: =SUM(F8:F14) -> 64710398
A16: в т.ч. НР | F16: 16257460
A17: в т.ч. СП | F17: 7700902
A19: ✅ МАЛЫЙ БЛОК — ОБОСНОВАН (жёсткие поперечины П-перехода, монтаж над путями)
A20: Поз. | B20: Расценка ГЭСНм | C20: Ед. | D20: Объём | F20: ВСЕГО по позиции, ₽
A21: 49 | B21: ГЭСНм20-035-02 | C21: км | D21: 0.72 | F21: 288549.74
A22: 50 | B22: ГЭСНм20-035-04 | C22: км | D22: 0.12 | F22: 11050.69
A23: 51 | B23: ГЭСНм20-035-03 | C23: км | D23: 0.36 | F23: 78031.82
A24: 52 | B24: ГЭСНм20-035-05 | C24: км | D24: 0.12 | F24: 25844.84
A25: 53 | B25: ГЭСНм20-035-06 | C25: км | D25: 0.12 | F25: 26005.07
A26: 54 | B26: ГЭСНм20-035-03 | C26: км | D26: 0.48 | F26: 104042.45
A27: 55 | B27: ГЭСНм20-035-07 | C27: шт | D27: 3 | F27: 776204.69
A28: ИТОГО малый блок | F28: =SUM(F21:F27) -> 1309729.3
A30: ℹ ЗАЗЕМЛЕНИЕ ОПОР (ГЭСНм20-02-023) — обосновано, НЕ часть «выноса»
A31: Поз. | B31: Расценка | C31: Ед. | D31: Объём | F31: ВСЕГО, ₽
A32: 44 | B32: ГЭСНм20-02-023-01 | C32: шт | D32: 3 | F32: 14965.13
A33: 56 | B33: ГЭСНм20-02-023-01 | C33: шт | D33: 127 | F33: 633523.97
A34: ИТОГО заземление | F34: =SUM(F32:F33) -> 648489.1
A36: ВЫВОД. Большой блок 64 710 398 ₽ — «воздух» при твёрдой цене (незакрываемо при КС-2: нельзя актировать невыполненный вынос) ИЛИ реальная работа с «окнами» РЖД и бригадой ЭЧ, если РЖД подтвердит. Снимается ценовым аудитом Гл.12 ССРСС. Без письменного ответа РЖД/Заказчика — ВОР возвращаю (согласна с ИИ-ГИП). Точная сумма — моя (ИИ-ГИП оценивал 45-55 млн, по ЛСР точно 64,71 млн).

Sheet 06_Матер_Оборуд
A1: СМЕТА vs СПЕЦИФИКАЦИЯ ПД — ЧЕГО НЕ ХВАТАЕТ (флаги 3, 4)
A2: Материалы 1,86 млн + оборуд 2,22 млн — аномально мало для объекта с таким «железом»
A4: А. ЧТО ЕСТЬ В СМЕТЕ
A5: Статья | B5: В смете, ₽ | D5: Комментарий
A6: Материалы (все ЛСР) | B6: 1862206.2 | D6: ЭОМ 1 596 779 + СОТ 265 428. Аномально мало
A7: Оборудование (СОТ) | B7: 2222036.3 | D7: в т.ч. монтаж; «железо» ПД не заведено
A8: из них криптошлюзы ViPNet | B8: 1386844.6 | D8: единственное реальное оборудование в смете
A10: Б. ЧТО В ПД, НО НЕ В СМЕТЕ КАК ПОСТАВКА (объём не определён)
A11: Позиция ПД (спецификация) | B11: Кол-во | C11: Ориентир рынка | D11: Статус
A12: Камеры видеонаблюдения | B12: 202 шт (смета 191) | C12: десятки млн | D12: 🔴 не как поставка; Δ11 шт + разрешение 4/8/16 Мп расходится
A13: Серверы СХД 384 Тб | B13: 2 шт | C13: высокий | D13: 🔴 отсутствует
A14: РЛС Orwell-R | B14: 8 модулей | C14: высокий | D14: 🔴 отсутствует
A15: Радиолучевые извещатели НЕО | B15: 8 шт | C15: средний | D15: 🔴 отсутствует
A16: Коммутаторы уличные | B16: 36 шт | C16: средний | D16: 🔴 отсутствует
A17: ИБП | B17: компл. | C17: средний | D17: 🔴 отсутствует
A18: Блок-контейнер | B18: чертёж 2 / смета 1 | C18: — | D18: 🟡 расхождение количества
A20: ВЫВОД для сметы: если оборудование в НАШЕМ объёме — себестоимость занижена на десятки млн, объект глубоко убыточен. Если давальческое / отдельный договор поставки — наша выручка = только монтаж (что и заведено). ВОПРОС ОБЪЁМА — ИИ-договорник+ИИ-снабженец (флаг 3). До ответа ВОР по оборудованию не закрываю.

Sheet 07_НР_СП
A1: РАЗЛОЖЕНИЕ НР / СП — ГДЕ ВИСИТ «ЖИРОК»
A2: НР+СП — плановая сметная маржа. Реальная маржа = «жирок» минус реальные косвенные, минус НДС-разрыв, минус простои РЖД
A4: Показатель | B4: ₽ | C4: Доля | D4: Комментарий
A5: Накладные расходы (НР), всего | B5: 26958200 | D5: пр.812/пр. Покрытие косвенных, НЕ прибыль
A6: Сметная прибыль (СП), всего | B6: 13513770 | D6: пр.774/пр. Плановая прибыль ≈12,6% Гл.1-9
A7: НОМИНАЛЬНЫЙ ЗАПАС НР+СП («жирок») | B7: =B5+B6 -> 40471970 | D7: весь сметный «жирок» объекта
A9: СКОЛЬКО «ЖИРКА» ВИСИТ НА БЛОКЕ КС (воздух)
A10: НР на большом блоке КС | B10: 16257460
A11: СП на большом блоке КС | B11: 7700902
A12: ИТОГО НР+СП на воздухе | B12: =B10+B11 -> 23958362 | C12: =B12/B7 -> 0.59197419 | D12: доля «жирка» на невыполнимом блоке
A13: РЕАЛЬНЫЙ запас НР+СП (без блока КС) | B13: =B7-B12 -> 16513608 | D13: вот из этого и делается маржа на реальных работах
A15: КЛЮЧЕВОЙ ВЫВОД. Из ≈40,5 млн сметного «жирка» НР+СП почти 24 млн (59%) висит на блоке «выноса КС», который проектом не обоснован. Убери блок — «жирок» падает до ≈16,5 млн на реальные ~40 млн работ. Реальная маржа тонкая и зависит от косвенных, НДС-разрыва и простоев РЖД. Это и есть причина заключения 🟡.

Sheet 08_Пересчёт_2026
A1: ПЕРЕСЧЁТ II кв.2025 → 2026 + НДС 22% (флаги 7 и 1)
A2: Смета в текущем уровне цен II кв.2025. Исполнение 2026 → нужна актуализация индексов и ставки НДС
A4: А. РЕИНДЕКС (флаг 7) — ПРЕДПОЛОЖЕНИЕ, подтвердить
A5: Параметр | B5: Значение | D5: Источник / статус
A6: База СМР+монтаж без НДС (II кв.2025) | B6: 100630000 | D6: СМР 20 957 + монтаж 79 662 тыс (Гл.1-9 без оборуд/прочих)
A7: Коэффициент реиндекса → 2026 | B7: 1.05 | D7: 🟨 РЕДАКТИРУЕМО. Ориентир: дефлятор СМР ~5%/год. Точную взять из письма Минстроя на квартал производства (УрФО/Курган). Индексы выходят поквартально; письмо на II кв.2026 № 37404-ИФ/09 от 23.07.2026
A8: Удорожание себестоимости (ориентир) | B8: =B6*(B7-1) -> 5031500 | D8: при твёрдой цене от II кв.2025 — съедает маржу молча
A10: Б. НДС 20% → 22% (флаг 1) — ФЗ 425-ФЗ от 28.11.2025
A11: Параметр | B11: Значение | D11: Комментарий
A12: База без НДС (Итого без НДС по ССРСС) | B12: 1.0707624e+08
A13: НДС по смете 20% | B13: =B12*0.2 -> 21415247
A14: НДС по закону 22% (работы 2026) | B14: =B12*0.22 -> 23556772
A15: НЕДОБОР НДС при твёрдой цене | B15: =B12*(0.22-0.2) -> 2141524.7 | D15: ≈2,14 млн ₽ съедает подрядчик, если цена «с НДС» фиксирована

Sheet 09_Конъюнктура
A1: КОНЪЮНКТУРА — РЫНОЧНЫЕ ОРИЕНТИРЫ ПО КЛЮЧЕВЫМ РЕСУРСАМ
A2: Флаг ИИ-руководителя проекта: СИП-4, ВОК, металл опор, ж/б плиты. Ориентир ±15% — для КП ИИ-снабженца (не замена КП)
A4: Материалы в РИМ «зашиты» в позиции (база всего 1,86 млн). Ниже — физобъёмы из ЛСР и рыночные ориентиры для проверки ИИ-снабженцем. СИП-4 4,96 км — «эталон честного счёта» (ИИ-ГИП: смета = кабельный журнал РД, Δ0,1%).
A6: Ресурс | B6: Ед. | C6: Объём | D6: Рынок мин, ₽/ед | E6: Рынок макс, ₽/ед | F6: Ориентир суммы / примечание
A7: СИП-4 4×25 (подвеска) | B7: м | C7: 4960 | D7: 110 | E7: 140 | F7: эталон РД; ~0,55-0,70 млн; источник: рынок РФ 2026 ~130 ₽/м
A8: Опоры металлические (с пути) | B8: шт | C8: 133 | D8: — | E8: — | F8: 6 шт св.массой + 127 шт до массы; КП по массе/марке — ИИ-снабженец
A9: Анкеры ж/б (фундаменты) | B9: шт | C9: 133 | D9: — | E9: — | F9: 1 анкер на опору
A10: Плиты ж/б дорожные (под б/к) | B10: м³ | C10: 5.04 | D10: — | E10: — | F10: ГЭСН27-06; ПП-6 6000×2000×140
A11: ВОК одномод | B11: м | C11: — | D11: — | E11: — | F11: по кабельному журналу РД — уточнить у ИИ-снабженца/ИИ-ПТО
A12: Прокат листовой Ст3 | B12: т | C12: 0.078 | D12: 60000 | E12: 66000 | F12: смета 62 596 ₽/т — в рынке
A14: Конъюнктура здесь — второстепенный рычаг: вся материальная база 1,86 млн против блока КС 64,7 млн. Реальные КП с логистикой до ст. Зауралье (плечо ~2000 км от Москвы, +5-12%) — задача ИИ-снабженца. Живые цены заменят эти ориентиры.

Sheet 10_Финрезультат
A1: ВЛИЯНИЕ НА МАРЖУ — 3 СЦЕНАРИЯ ПО РАЗРЕШЕНИЮ БЛОКА КС
A2: Знак маржи определяется судьбой блока «выноса КС». Красная линия 5% (ИИ-руководитель проекта). Три варианта — решение за ИИ-руководителем проекта
A4: Базовая НМЦК (потолок цены) = 128 491 484 ₽ с НДС / 107 076 237 ₽ без НДС. Всё упирается в блок КС 64,71 млн: реальная выручка это или «воздух»? Плюс сквозные вычеты: двойной ПНР, НДС-разрыв, реиндекс.
A6: Статья (без НДС) | B6: А. РЖД подтвердил вынос КС | C6: Б. Объём КС снят (ценовой аудит Гл.12) | D6: В. Тверд. цена, вынос не делаем | E6: Комментарий
A7: Собираемая выручка (без НДС) | B7: 104086033 | C7: 39375635 | D7: 39375635 | E7: А: полная; Б/В: минус блок КС 64,71 млн (в В деньги за невыполненный вынос НЕ поступят — нельзя актировать при КС-2)
A8: − Реальная себестоимость работ | B8: -85000000 | C8: -30000000 | D8: -30000000 | E8: труд+ЭМ+материалы+реальные НР; А: +реальный вынос КС, «окна» РЖД, бригада ЭЧ
A9: − Двойной счёт ПНР (уйдёт при аудите) | B9: -890670 | C9: -890670 | D9: -890670 | E9: воздух в цене, незакрываемо
A10: − НДС-разрыв 20%→22% | B10: -2141525 | C10: -810000 | D10: -810000 | E10: при твёрдой цене «с НДС»; в Б/В база меньше
A11: − Реиндекс 2025→2026 (ориентир) | B11: -5000000 | C11: -2000000 | D11: -5000000 | E11: удорожание при твёрдой цене от II кв.2025
A12: − Простои РЖД / претензии / кассовый провал | B12: -6000000 | C12: 0 | D12: -8000000 | E12: А: риск простоев на выносе; В: акт разногласий, кассовый провал, риск ФАС
A13: ИТОГО ОЖИДАЕМАЯ МАРЖА (ориентир) | B13: =SUM(B7:B12) -> 5053838 | C13: =SUM(C7:C12) -> 5674965 | D13: =SUM(D7:D12) -> -5325035 | E13: диапазон, не точка — зависит от неизвестных
A14: % маржи к выручке | B14: =B13/B7 -> 0.04855443 | C14: =C13/C7 -> 0.14412377 | D14: =D13/D7 -> -0.1352368 | E14: красная линия 5%
A16: РЕКОМЕНДАЦИЯ ИИ-СМЕТЧИКА (решение — за ИИ-руководителем проекта)
A17: Базовый для планирования — СЦЕНАРИЙ Б (объём КС снят через запрос в РЖД / ценовой аудит Гл.12): честный объект ~40 млн работ, маржа реалистична при жёстком контроле. СЦЕНАРИЙ А приемлем ТОЛЬКО при письменном подтверждении РЖД + допуске бригады ЭЧ (риск простоев). СЦЕНАРИЙ В НЕ рекомендую — 79 млн «воздуха» нельзя закрыть при КС-2, кассовый провал + претензии/ФАС. До ответа РЖД себес недостоверен — финмодель ИИ-экономиста не строить на блоке КС как на выручке.
A18: ⚠ Цифры себестоимости в сценариях — ПРЕДПОЛОЖЕНИЯ (±) для оценки знака маржи, а не точный финансовый результат. Точный финансовый результат — ИИ-экономист (Такт 5) на подтверждённых объёмах ИИ-ГИП и КП ИИ-снабженца.

Sheet 11_Передачи_смежникам
A1: ПЕРЕДАЧИ СМЕЖНИКАМ КОМАНДЕ + АЛЕРТ ИИ-РУКОВОДИТЕЛЮ ПРОЕКТА
A2: Что несу дальше по конвейеру (порядок ИИ-руководителя проекта). Каждому — конкретная задача с денежным эффектом
A4: 🚨 СМЕТНЫЙ АЛЕРТ | 03.08.2026 Ситуация: блок «вынос КС» 64,71 млн (62% Гл.1-9) не обоснован РД + двойной счёт ПНР 0,89 млн + НДС-разрыв 2,14 млн. Сметный эффект: НМЦК завышена/недостоверна; из 40,5 млн «жирка» НР+СП 24 млн висит на воздухе. Документ: разбор готов (этот файл). Нужно решение ИИ-руководителя проекта: (1) эскалация запроса в РЖД по выносу КС; (2) запрос расшифровки объёма оборудования; (3) позиция по НДС 22% в договор.
A6: Кому | B6: Что несу / задача | C6: Приоритет
A7: → ИИ-руководителю проекта (РП) | B7: 3 красных флага подтверждаю и оцифровываю: КС 64,71 млн (не 45-55), двойной ПНР 0,89 млн, НДС-разрыв 2,14 млн. Заключение 🟡 поддерживаю. Рекомендация — сценарий Б. | C7: КРИТ
A8: → ИИ-экономисту (Эконом) | B8: БЕЗ ответа РЖД финмодель не строить на блоке КС как на выручке. 3 сценария (лист 10) — вход в финансовый результат. Учесть НДС 22% (−2,14 млн), двойной ПНР (−0,89 млн), реиндекс. | C8: ВЫСОКИЙ
A9: → ИИ-снабженцу (Снаб) | B9: Оборудование СОТ (202 камеры, 2×СХД, 8×РЛС, 8×НЕО, 36 коммут., ИБП) — наша поставка или давальческое? КП + сроки поставки до ст. Зауралье. Сверить разрешение камер (4/8/16 Мп). СИП-4 4×25 4,96 км, металл опор 133, плиты ж/б. | C9: ВЫСОКИЙ
A10: → ИИ-подрядчику (Подряд) | B10: Если РЖД подтвердит вынос КС — нужен подрядчик с допуском к работам на контактной сети 27,5 кВ и в «окна» (бригада ЭЧ). Спецтехника: автогидроподъёмник, вибропогружатель — аренда vs субподряд. | C10: СРЕДНИЙ
A11: → ИИ-ПТО (ПТО) | B11: На КС-2 нельзя закрыть невыполненный «вынос КС» — держать под контролем. ИД под ж/д + категорированный объект: аккредит. электролаборатория, допуски РЖД, спецпроверки ФСБ. | C11: СРЕДНИЙ
A12: → ИИ-договорнику (Договор) | B12: Официальные запросы Заказчику/РЖД: (1) фактически требуемый вынос КС; (2) объём оборудования — давальческое/отд. договор; (3) НДС 22% формулировка; (4) устранить двойной ПНР в НМЦК; (5) чьи риски простоя по «окнам». | C12: КРИТ
A13: → ИИ-администратору (Админ) | B13: Внести находки в реестр поручений с датами. Статус ВОР = 🔴 возвращён (согласовано с ИИ-ГИП). Собрать пакет к возврату ИИ-руководителю проекта. | C13: СРЕДНИЙ
A15: Разграничение с ИИ-ГИП: объём и состав (что и сколько, обосновано физикой/РД) — его зона; цена, индекс, НР/СП, сходимость, двойной счёт — моя. Блок КС вернули оба: он — по геометрии/РД, я — по деньгам и незакрываемости при КС-2. ИИ-сметчик · Сметчик · СтройИнтеллект v8.2 · 03.08.2026
