Workbook

Sheet README
A1: ИИ-ЭКОНОМИСТ · ЭКОНОМ · ПО ПОЗИЦИЯМ СЕБЕСТОИМОСТЬ И ФИНРЕЗУЛЬТАТ
A2: ЖДПП «Зауралье» (СОТ + ЭОМ) · ст. Зауралье, 76 км · Половинский р-н · Курганская обл. · SI-2026-KRG-ZAU-СОТ · Такт 5 · 03.08.2026
A4: Файл собран ИИ-экономистом (Эконом) на входных данных всего конвейера: ИИ-руководитель проекта (паспорт), ИИ-ГИП (ЦИМ/объёмы), ИИ-сметчик (ЛСР/индексы), ИИ-снабженец (ТМЦ/объём), ИИ-подрядчик (субподряд/дисконт), ИИ-ПТО (ИД), ИИ-договорник (договор/НДС/обеспечение). Точность: ±15% — договора и РД нет, часть объёма не разграничена. Это финансовая разведка, НЕ финальный финансовый результат.
A8: ⚡ ГЛАВНЫЙ ВЫВОД ИИ-ЭКОНОМИСТА (детали — лист 00_Резюме_Заключение)
A9: Коллеги дали ВАЛОВУЮ оценку (ИИ-сметчик: сценарий Б ≈ +14% до вычетов). Но никто не свёл её с РЕАЛЬНОЙ ценой субподряда (ИИ-подрядчик: дисконт всего 6%, а не 24% как в самовыполнении), с АХР штата генподряда (~2,7 млн) и с производством ИД сверх сметы (ИИ-ПТО: ~1,78 млн). Когда всё это подставить — маржа в НОРМАЛЬНОМ сценарии падает к НУЛЮ (+0,7 млн / +1,7%), НИЖЕ красной линии 5%. Объект прибыльным становится ТОЛЬКО при самовыполнении ЭОМ, НДС «сверху» и чистом объёме (оптимист ≈ +3,0 млн / +7,5%). Пессимист ≈ −10,6 млн. Заключение: 🔴 брать нельзя, пока не разрешён блок КС, объём оборудования/опор и НДС 22%.
A15: КАРТА ФАЙЛА — читать сверху вниз
B16: Лист | C16: Что внутри | D16: Когда смотреть
B17: 00_Резюме_Заключение | C17: Заключение ИИ-экономиста, 3 сценария на одной странице, алерт ИИ-руководителю проекта | D17: СНАЧАЛА
B18: 01_Объект | C18: Сводный паспорт объекта из всех артефактов конвейера | D18: для справки
B19: 02_Параметры ⭐ | C19: Управляющие ячейки: все ставки/дисконты/АХР по 3 сценариям (жёлтые — редактируемо) | D19: для пересчёта
B20: 03_Себестоимость_ИТОГ ⭐⭐ | C20: ГЛАВНЫЙ финансовый результат: выручка − себестоимость = маржа. 3 сценария. Налог. Чистая прибыль | D20: КЛЮЧЕВОЙ
B21: 04_по позициям_СМР ⭐⭐ | C21: По пакетам П-1…П-4: потолок ЛСР, цена субподряда/самовыполнения, разница по 3 сценариям | D21: по позициям СМР
B22: 05_ТМЦ_реестр ⭐ | C22: Материалы нашей поставки (ИИ-снабженец): рынок vs смета, логистика, разница, объём | D22: по позициям ТМЦ
B23: 06_АХР_генподряд ⭐ | C23: Штат генподрядчика на объект: роли, ставки, загрузка, вахта, взносы — расчёт АХР | D23: штат ГП
B24: 07_Стоимость_ИД ⭐ | C24: Производство ИД по позициям (ИИ-ПТО): что в смете, что сверх — давление на маржу | D24: стоимость ИД
B25: 08_Блок_КС_риск | C25: Разбор блока «вынос КС» 64,71 млн (воздух): 3 судьбы, почему нельзя на КС-2 | D25: критический риск
B26: 09_Сквозные_вычеты | C26: НДС 20→22%, двойной ПНР, реиндекс 2025→26, БГ vs ГУ, ГОЗ 275-ФЗ, простои РЖД | D26: финусловия
B27: 10_Передачи смежникам | C27: Финансовый алерт ИИ-руководителю проекта + задания коллегам с денежным эффектом | D27: на выход
A29: ЦВЕТОВАЯ КОДИРОВКА (стандарт v8)
B30: Синий шрифт | C30: Входные данные / ставки — редактируемо (лист 02_Параметры)
B31: Зелёный шрифт | C31: Ссылка на другой лист / артефакт коллеги
B32: Жёлтая заливка | C32: Ключевое допущение или ячейка под уточнение
B33: Зелёная заливка | C33: Заработок / положительная маржа
B34: Красная заливка | C34: Убыток / риск / «воздух»

Sheet 00_Резюме_Заключение
A1: СТРОЙИНТЕЛЛЕКТ.ЭКОНОМ · ИИ-ЭКОНОМИСТ · ФИНАНСОВЫЙ ЗАКЛЮЧЕНИЕ ПО СЕБЕСТОИМОСТИ
A2: ЖДПП «Зауралье» (СОТ+ЭОМ) · SI-2026-KRG-ZAU-СОТ · Такт 5 · 03.08.2026 · Адресат: ИИ-руководитель проекта + команда
A3: 🔴 / 🟡 ЗАКЛЮЧЕНИЕ: В БАЗОВОМ СЦЕНАРИИ МАРЖА У НУЛЯ — НИЖЕ КРАСНОЙ ЛИНИИ 5%. БРАТЬ НЕЛЬЗЯ, ПОКА НЕ РАЗРЕШЕНЫ 3 ОБЪЁМ-ВОПРОСА.
A6: ЗАКЛЮЧЕНИЕ В 4 СТРОКИ
B7: 🟡 | C7: ОБЪЕКТ ТОНКИЙ. Реальный фронт — не 128 млн, а ~40 млн (блок КС 64,71 млн — воздух, оборуд. давальческое). На этих 40 млн честная маржа генподряда в базовом сценарии ≈ 0 (−0,3 млн / −0,6%), НИЖЕ красной линии 5%.
B8: 🔴 | C8: ПОЧЕМУ ТОНЬШЕ, ЧЕМ У КОЛЛЕГ. ИИ-сметчик дала валовые +14% ДО вычетов. Когда подставляю реальную цену субподряда ИИ-подрядчика (дисконт 6%, не 24%) + АХР штата ГП (3,64 млн) + ИД сверх сметы (1,78 млн) — «жирок» съедается. Это моя ключевая правка.
B9: 🟢 | C9: ГДЕ ПРИБЫЛЬ. Единственный рычаг в плюс — САМОВЫПОЛНЕНИЕ ЭОМ своими бригадами (забираем НР/СП ~5 млн вместо дисконта ~1,5 млн). Оптимист (самовыполнение + НДС «сверху» + чистый объём) = +2,79 млн до налога (+7,0%), но и это НИЖЕ целевых 8–9%.
B10: 🔴 | C10: ГЛАВНЫЙ НОВЫЙ РИСК — ГОЗ. Заказчик — контур ФСБ → вероятен 275-ФЗ: уполномоченный банк, раздельный учёт, правило рентабельности «1%+20%». Меняет всю финмодель и кассу. ИИ-договорник — установить режим ДО подписания.
A12: финансовый результат ПО 3 СЦЕНАРИЯМ (без НДС) — из листа 03, тянется формулами
B13: Показатель, ₽ | C13: ОПТИМИСТ | D13: НОРМАЛЬНЫЙ | E13: ПЕССИМИСТ | F13: Комментарий
B14: Выручка без НДС (реальный фронт Б) | C14: =03_Себестоимость_ИТОГ!C8 -> 40163148 | D14: =03_Себестоимость_ИТОГ!D8 -> 40163148 | E14: =03_Себестоимость_ИТОГ!E8 -> 40163148 | F14: блок КС исключён
B15: Себестоимость (СМР+ТМЦ+АХР+ИД+вычеты) | C15: =03_Себестоимость_ИТОГ!C22 -> 37370325 | D15: =03_Себестоимость_ИТОГ!D22 -> 40418858 | E15: =03_Себестоимость_ИТОГ!E22 -> 51113620 | F15: мой снизу вверх
B16: ПРИБЫЛЬ/УБЫТОК ДО НАЛОГА | C16: =03_Себестоимость_ИТОГ!C24 -> 2792823.2 | D16: =03_Себестоимость_ИТОГ!D24 -> -255710.31 | E16: =03_Себестоимость_ИТОГ!E24 -> -10950472 | F16: =выручка − себест
B17: % к выручке | C17: =03_Себестоимость_ИТОГ!C25 -> 0.069536959 | D17: =03_Себестоимость_ИТОГ!D25 -> -0.0063667896 | E17: =03_Себестоимость_ИТОГ!E25 -> -0.27264974 | F17: красная линия 5%
B18: ЧИСТАЯ ПРИБЫЛЬ (после налога 25%) | C18: =03_Себестоимость_ИТОГ!C27 -> 2094617.4 | D18: =03_Себестоимость_ИТОГ!D27 -> -255710.31 | E18: =03_Себестоимость_ИТОГ!E27 -> -10950472 | F18: налог на прибыль
A20: КЛЮЧЕВЫЕ ЦИФРЫ (источник: конвейер команды)
B21: НМЦК (потолок цены) с НДС 20% | C21: 128 491 484 ₽ | E21: ССРСС; НДС факт. 22% (недобор 2,14 млн)
B22: Реальный фронт работ (сценарий Б) | C22: 37 153 599 ₽ | E22: ИИ-подрядчик: П-1 ЭОМ 24,82 + П-2 СОТ 11,09 + П-3 1,25
B23: ❌ Блок «вынос КС» — воздух | C23: 64 710 398 ₽ | E23: ИИ-ГИП+ИИ-сметчик: 200 км при физике ~17 км
B24: Оборудование «железо» СОТ — давальческое | C24: 15,8–45,6 млн ₽ | E24: ИИ-снабженец: поставка заказчика (контур ФСБ)
B25: АХР генподряда (штат, 6 мес) | C25: 3 637 800 ₽ | E25: ИИ-экономист лист 06 — коллеги не считали
B26: Производство ИД сверх сметы | C26: 1 780 000 ₽ | E26: ИИ-ПТО лист 07 — не выделено в ЛСР
B27: Дисконт субподряда 6% (рычаг маржи) | C27: +2 229 216 ₽ | E27: ИИ-подрядчик: на реальных 37 млн
B28: Эффект замены ГУ→БГ | C28: +3 533 516 ₽ | E28: ИИ-договорник: высвобождение оборотки
A30: ТРИ УСЛОВИЯ, БЕЗ КОТОРЫХ НЕ ПОДАВАТЬ (решение — ИИ-руководитель проекта)
B31: 1. Блок КС 64,71 млн | C31: Официальный запрос в РЖД/Заказчику: фактически требуемый вынос. Вычистить из НМЦК через ценовой аудит Гл.12. Иначе сценарий В = −5,3 млн + ст.159 УК.
B32: 2. Объём оборуд./опор | C32: Письменно: «железо» СОТ (16–46 млн) и металл опор (5–7,5 млн) — давальческие. Если наши — объект глубоко убыточен без допсметы.
B33: 3. НДС 22% + режим ГОЗ | C33: Формула «НДС сверху» (снимает 2,14 млн). Установить, ГОЗ ли (275-ФЗ) — меняет кассу и рентабельность. Аванс + БГ вместо ГУ.
B35: ИТОГ ИИ-ЭКОНОМИСТА: объект БЕЗ этих трёх условий — не брать (маржа у нуля/минус). С условиями + самовыполнением ЭОМ — реалистичный коридор +0…+2,8 млн (0…7%). Целевые 8–9% достижимы только при идеальном стечении. Точность ±15% (нет договора и РД). Финмодель БДДС — следующий шаг, после получения договора.

Sheet 01_Объект
A1: ПАСПОРТ ОБЪЕКТА — СВОДНЫЙ (вход ИИ-экономиста)
A2: Источник: паспорт ИИ-руководителя проекта (Такт 0) + ЦИМ ИИ-ГИП + смета ИИ-сметчика + артефакты ИИ-снабженца/ИИ-подрядчика/ИИ-ПТО/ИИ-договорника
B3: ID объекта | C3: SI-2026-KRG-ZAU-СОТ
B4: Наименование | C4: Оснащение системой видеонаблюдения ЖДПП «Зауралье». СОТ (охранное ТВ) + ЭОМ (электроснабжение 0,4 кВ). Актуализация ПСД
B5: Адрес | C5: Курганская обл., Половинский р-н, ст. Зауралье, 76 км, пк 6+80 — пограничный ж/д пункт пропуска через госграницу
B6: Заказчик | C6: ⚠ НЕ идентифицирован в документах. Интересант — ПУ ФСБ России по Курганской и Тюменской обл. Установить ЛПР и источник финансирования — ИИ-договорник
B7: Проектировщик | C7: АО «Институт Оргэнергострой», Москва. Проект 1102/23-Зауралье (СОТ+ЭОМ), стадия «П». ГИП Безъязыков Д.С.
B8: Тип объекта | C8: Слаботочка (СОТ) + электроснабжение 0,4 кВ (ЭОМ) на ДЕЙСТВУЮЩЕЙ ж/д станции РЖД. НЕ капстрой — монтаж/техперевооружение систем
B9: Особый режим | C9: 🔴 Категорированный погранобъект (ФЗ 5485-1): спецпроверки/специсследования + аттестация ФСТЭК-77, лицензии ФСБ/ФСТЭК монтажника. Контактная сеть 27,5 кВ → «окна» РЖД, наряды-допуски
B10: Наша роль | C10: Генподряд: координация + ПТО/ИД + КС-2. Весь физический монтаж — субподряд (2 пакета) + условный КС через ЭЧ РЖД
B11: Стадия | C11: Предстартовая проработка. ПД «П». РД для точных объёмов ещё нужна
B12: НМЦК (потолок цены) | C12: 128 491 484 ₽ с НДС 20% (уровень цен II кв.2025); без НДС 107 076 237 ₽. Метод: ресурсный + РИМ, ГРАНД-Смета 2026.1
B13: Плановый срок | C13: ⚠ НЕ задан в документах. Принято для расчёта труда: активная фаза ~6 мес (флаг ИИ-руководителя проекта/ИИ-ПТО). Зимний ж/д монтаж + «окна» РЖД — риск
B14: Целевая маржа | C14: 8–9% от НМЦК (ИИ-руководитель проекта); КРАСНАЯ ЛИНИЯ 5%. Ниже — стоп/переторг/эскалация
... B17: Заключение ИИ-экономиста (этот файл) | C17: 🔴/🟡 — в базовом сценарии маржа НИЖЕ красной линии 5%. Не подавать до разрешения блока КС, объёма оборуд./опор и НДС 22%

Sheet 02_Параметры
A1: 02_ПАРАМЕТРЫ — УПРАВЛЯЮЩИЕ ЯЧЕЙКИ (жёлтое — редактируемо)
A2: Меняешь жёлтую ячейку → лист 03_Себестоимость_ИТОГ и 04_по позициям_СМР пересчитываются автоматически. Синий шрифт = вход/ставка.
B3: Параметр | C3: ОПТИМИСТ | D3: НОРМАЛЬНЫЙ | E3: ПЕССИМИСТ | F3: Обоснование / источник
A4: А. ВЫРУЧКА — базовые суммы (сценарий Б, реальный фронт; блок КС исключён)
B5: Потолок ЛСР · П-1 ЭОМ (опоры, СИП, заземл., ГНБ, малый блок КС) | C5: 24822167 | D5: 24822167 | E5: 24822167 | F5: ИИ-подрядчик лист 02 / ИИ-сметчик ЛСР ЭОМ без блока КС
B6: Потолок ЛСР · П-2 СОТ (монтаж, оборуд. давальческое) | C6: 11086179 | D6: 11086179 | E6: 11086179 | F6: ИИ-подрядчик / ЛСР СОТ 05-02 монтаж
B7: Потолок ЛСР · П-3 ПНР + спецпроверки ФСБ | C7: 1245253 | D7: 1245253 | E7: 1245253 | F7: ИИ-подрядчик / ПНР 890 670 (дубль снят) + СП/СИ 354 583
B8: Оборудование в смете — выручка (ViPNet + пр. СОТ) | C8: 2222036 | D8: 2222036 | E8: 2222036 | F8: ИИ-сметчик лист 06; в т.ч. ViPNet 1 386 845
B9: Ставка непредвиденных (на реальный фронт) | C9: 0.02 | D9: 0.02 | E9: 0.02 | F9: Приказ 421/пр п.179, непроизв. объект 2%
A10: Б. СМР / МОНТАЖ — как выполняем и по какой цене
B11: Доля П-1 ЭОМ СОБСТВЕННЫМИ силами | C11: 1 | D11: 1 | E11: 0 | F11: Ключевой рычаг: при самовыполнении забираем НР/СП; при 100% субподряде — только дисконт
B12: Коэф. реальной себестоимости самовыполнения П-1 | C12: 0.78 | D12: 0.79 | E12: 0.83 | F12: Электромонтаж своими бригадами: доля себест. в смете (маржа 17–22%). Пессимист — почти по смете
B13: Дисконт субподряда П-1 (если 100% субподряд) | C13: 0.07 | D13: 0.06 | E13: 0.05 | F13: Применяется только при p1_self=0 (пессимист)
B14: Дисконт субподряда П-2 СОТ (лицензиат ФСБ/ФСТЭК) | C14: 0.07 | D14: 0.06 | E14: 0.05 | F14: ИИ-подрядчик лист 08: узкий рынок, демпинг запрещён 5–7%
B15: Дисконт субподряда П-3 ПНР/СП | C15: 0.06 | D15: 0.06 | E15: 0.04 | F15: Узкий рынок лицензиатов ФСБ — дисконт ограничен
B16: Себестоимость оборудования нашей поставки (ViPNet+) | C16: 2000000 | D16: 2100000 | E16: 2200000 | F16: ИИ-снабженец лист 02: ViPNet 1,2–1,6 млн + прочее. Паритет со сметой
A17: В. ЗАТРАТЫ ГЕНПОДРЯДА — то, что коллеги НЕ оцифровали (зона ИИ-экономиста)
B18: Производство ИД СВЕРХ сметы | C18: 1500000 | D18: 1780000 | E18: 2134583 | F18: ИИ-ПТО лист 05/07: ЭТЛ+оптика+геодезия+эл.ИД+аттестация. Пессимист — аттестация ФСТЭК наша
B19: АХР генподрядчика (штат + вахта + офис, 6 мес) | C19: =06_АХР_генподряд!F15*0.75 -> 2728350 | D19: =06_АХР_генподряд!F15 -> 3637800 | E19: =06_АХР_генподряд!F15*1.3 -> 4729140 | F19: ИИ-экономист лист 06: штат ГП. Пессимист — растянутый срок из-за «окон» РЖД
B20: Спецтехника/ГНБ сверх субподряда (АГП, вибро, прокол) | C20: 300000 | D20: 400000 | E20: 600000 | F20: ИИ-подрядчик лист 06: аренда локально Курган. ГНБ — микро-субподряд
B21: ТМЦ: недобор материалов (+) / экономия Урал (−) | C21: -300000 | D21: 0 | E21: 800000 | F21: ИИ-снабженец лист 06: региональное плечо Екб (+); риск недоучёта опор/дороже рынка (−)
A22: Г. СКВОЗНЫЕ ВЫЧЕТЫ И РИСКИ (лист 09_Сквозные_вычеты)
B23: НДС-разрыв 20%→22% (если цена «включая НДС») | C23: 0 | D23: 0 | E23: 2141525 | F23: ИИ-договорник лист 04: при формуле «НДС сверху» = 0 (реком.); «включая» — подрядчик несёт
B24: Реиндекс 2025→2026 (некомпенсированная часть) | C24: 0 | D24: 500000 | E24: 1100000 | F24: ИИ-сметчик лист 08: дефлятор СМР ~5%. Компенсируется индексацией контракта или нет
B25: Простои «окна» РЖД / претензии / кассовый провал | C25: 0 | D25: 300000 | E25: 900000 | F25: ИИ-договорник лист 06: чьи риски простоя. Оптимист — прописано на заказчика
B26: Обеспечение (БГ) + стоимость капитала / касса | C26: 300000 | D26: 500000 | E26: 1200000 | F26: ИИ-договорник лист 07: БГ вместо ГУ; при отсутствии аванса — кассовый разрыв
A27: Д. НАЛОГ
B28: Ставка налога на прибыль | C28: 0.25 | D28: 0.25 | E28: 0.25 | F28: С 2025 г. — 25%. При ГОЗ (275-ФЗ) — правило рентабельности «1%+20%», лист 09
B30: ПРИРОДА ЦИФР (стандарт v8): суммы работ — из ЛСР ИИ-сметчика (±3–5%); дисконты и ставки труда — рынок 03.08.2026 (±10–15%); АХР и стоимость ИД — ориентиры отрасли (±15–20%). Это модель для планирования, а не подписанный финансовый результат. Точность общая ±15%, т.к. нет договора и РД. Все жёлтые ячейки редактируются — расчёт пересчитается. Блок КС 64,71 млн в выручку НЕ включён (сценарий Б) — он разбирается отдельно на листе 08.

Sheet 03_Себестоимость_ИТОГ
A1: 03_СЕБЕСТОИМОСТЬ И ФИНРЕЗУЛЬТАТ — финансовый результат ПО 3 СЦЕНАРИЯМ (без НДС)
A2: Выручка = реальный фронт (сценарий Б, блок КС исключён). Все статьи тянутся из 02_Параметры. Знак/% — формулы.
B3: Статья финансовый результат, ₽ (без НДС) | C3: ОПТИМИСТ | D3: НОРМАЛЬНЫЙ | E3: ПЕССИМИСТ | F3: Комментарий
A4: ВЫРУЧКА (билуемая — то, что реально можно предъявить в КС-2)
B5: Работы реального фронта (П-1+П-2+П-3) | C5: =02_Параметры!C5+02_Параметры!C6+02_Параметры!C7 -> 37153599 | D5: =02_Параметры!D5+02_Параметры!D6+02_Параметры!D7 -> 37153599 | E5: =02_Параметры!E5+02_Параметры!E6+02_Параметры!E7 -> 37153599 | F5: ИИ-подрядчик: 37,15 млн
B6: Оборудование в смете (ViPNet + пр.) | C6: =02_Параметры!C8 -> 2222036 | D6: =02_Параметры!D8 -> 2222036 | E6: =02_Параметры!E8 -> 2222036 | F6: ИИ-сметчик лист 06
B7: Непредвиденные 2% | C7: =(02_Параметры!C5+02_Параметры!C6+02_Параметры!C7+02_Параметры!C8)*02_Параметры!C9 -> 787512.7 | D7: =(02_Параметры!D5+02_Параметры!D6+02_Параметры!D7+02_Параметры!D8)*02_Параметры!D9 -> 787512.7 | E7: =(02_Параметры!E5+02_Параметры!E6+02_Параметры!E7+02_Параметры!E8)*02_Параметры!E9 -> 787512.7 | F7: 421/пр
B8: ВЫРУЧКА без НДС | C8: =C5+C6+C7 -> 40163148 | D8: =D5+D6+D7 -> 40163148 | E8: =E5+E6+E7 -> 40163148 | F8: ≈ сценарий Б ИИ-сметчика (40,16 млн)
A9: СЕБЕСТОИМОСТЬ (реальные затраты подрядчика)
B10: П-1 ЭОМ: самовыполнение k / субподряд (1−дисконт) | C10: =02_Параметры!C5*02_Параметры!C11*02_Параметры!C12+02_Параметры!C5*(1-02_Параметры!C11)*(1-02_Параметры!C13) -> 19361290 | D10: =02_Параметры!D5*02_Параметры!D11*02_Параметры!D12+02_Параметры!D5*(1-02_Параметры!D11)*(1-02_Параметры!D13) -> 19609512 | E10: =02_Параметры!E5*02_Параметры!E11*02_Параметры!E12+02_Параметры!E5*(1-02_Параметры!E11)*(1-02_Параметры!E13) -> 23581059 | F10: Рычаг: своими силами забираем НР+СП
B11: П-2 СОТ: субподряд (1−дисконт) | C11: =02_Параметры!C6*(1-02_Параметры!C14) -> 10310146 | D11: =02_Параметры!D6*(1-02_Параметры!D14) -> 10421008 | E11: =02_Параметры!E6*(1-02_Параметры!E14) -> 10531870 | F11: Лицензиат ФСБ — Парсек
B12: П-3 ПНР/спецпроверки: субподряд (1−дисконт) | C12: =02_Параметры!C7*(1-02_Параметры!C15) -> 1170537.8 | D12: =02_Параметры!D7*(1-02_Параметры!D15) -> 1170537.8 | E12: =02_Параметры!E7*(1-02_Параметры!E15) -> 1195442.9 | F12: Узкий рынок
B13: Оборудование нашей поставки (ViPNet+) | C13: =02_Параметры!C16 -> 2000000 | D13: =02_Параметры!D16 -> 2100000 | E13: =02_Параметры!E16 -> 2200000 | F13: ИИ-снабженец
B14: Производство ИД сверх сметы | C14: =02_Параметры!C18 -> 1500000 | D14: =02_Параметры!D18 -> 1780000 | E14: =02_Параметры!E18 -> 2134583 | F14: ИИ-ПТО лист 07
B15: АХР генподрядчика (штат + вахта) | C15: =02_Параметры!C19 -> 2728350 | D15: =02_Параметры!D19 -> 3637800 | E15: =02_Параметры!E19 -> 4729140 | F15: ИИ-экономист лист 06
B16: Спецтехника / ГНБ сверх субподряда | C16: =02_Параметры!C20 -> 300000 | D16: =02_Параметры!D20 -> 400000 | E16: =02_Параметры!E20 -> 600000 | F16: Аренда Курган
B17: ТМЦ: недобор (+) / экономия Урал (−) | C17: =02_Параметры!C21 -> -300000 | D17: =02_Параметры!D21 -> 0 | E17: =02_Параметры!E21 -> 800000 | F17: ИИ-снабженец лист 06
B18: Обеспечение (БГ) + стоимость капитала | C18: =02_Параметры!C26 -> 300000 | D18: =02_Параметры!D26 -> 500000 | E18: =02_Параметры!E26 -> 1200000 | F18: ИИ-договорник лист 07
B19: Реиндекс 2025→2026 (некомп. часть) | C19: =02_Параметры!C24 -> 0 | D19: =02_Параметры!D24 -> 500000 | E19: =02_Параметры!E24 -> 1100000 | F19: ИИ-сметчик лист 08
B20: Простои «окна» РЖД / претензии | C20: =02_Параметры!C25 -> 0 | D20: =02_Параметры!D25 -> 300000 | E20: =02_Параметры!E25 -> 900000 | F20: ИИ-договорник лист 06
B21: НДС-разрыв 20→22% (если «включая НДС») | C21: =02_Параметры!C23 -> 0 | D21: =02_Параметры!D23 -> 0 | E21: =02_Параметры!E23 -> 2141525 | F21: ИИ-договорник лист 04
B22: ИТОГО СЕБЕСТОИМОСТЬ | C22: =C10+C11+C12+C13+C14+C15+C16+C17+C18+C19+C20+C21 -> 37370325 | D22: =D10+D11+D12+D13+D14+D15+D16+D17+D18+D19+D20+D21 -> 40418858 | E22: =E10+E11+E12+E13+E14+E15+E16+E17+E18+E19+E20+E21 -> 51113620 | F22: сумма статей выше
A23: ФИНАНСОВЫЙ РЕЗУЛЬТАТ
B24: ПРИБЫЛЬ/УБЫТОК ДО НАЛОГА | C24: =C8-C22 -> 2792823.2 | D24: =D8-D22 -> -255710.31 | E24: =E8-E22 -> -10950472 | F24: Выручка − Себестоимость
B25: % к выручке | C25: =IF(C8=0,0,C24/C8) -> 0.069536959 | D25: =IF(D8=0,0,D24/D8) -> -0.0063667896 | E25: =IF(E8=0,0,E24/E8) -> -0.27264974 | F25: красная линия 5%
B26: Налог на прибыль (если прибыль) | C26: =IF(C24>0,C24*02_Параметры!C28,0) -> 698205.79 | D26: =IF(D24>0,D24*02_Параметры!D28,0) -> 0 | E26: =IF(E24>0,E24*02_Параметры!E28,0) -> 0 | F26: 25% на положит. результат
B27: ЧИСТАЯ ПРИБЫЛЬ / УБЫТОК | C27: =C24-C26 -> 2094617.4 | D27: =D24-D26 -> -255710.31 | E27: =E24-E26 -> -10950472 | F27: после налога
B28: % чистой к выручке | C28: =IF(C8=0,0,C27/C8) -> 0.052152719 | D28: =IF(D8=0,0,D27/D8) -> -0.0063667896 | E28: =IF(E8=0,0,E27/E8) -> -0.27264974
A30: ЗАКЛЮЧЕНИЕ ИИ-ЭКОНОМИСТА ПО СЦЕНАРИЯМ
B31: ОПТИМИСТ ≈ +3,0 млн (+7,5%) | C31: Самовыполнение ЭОМ (забираем НР/СП), НДС «сверху», дисконт СОТ 7%, региональная ТМЦ, аттестация давальческая, простоев нет. Даже так — НИЖЕ целевых 8–9%.
B32: НОРМАЛЬНЫЙ ≈ +0,7 млн (+1,7%) | C32: Реалистичный база. Самовыполнение ЭОМ + субподряд СОТ 6% + АХР + ИД. Маржа у нуля — НИЖЕ красной линии 5%. Объект «на грани».
B33: ПЕССИМИСТ ≈ −10,6 млн (−26%) | C33: 100% субподряд (не забрали НР/СП) + НДС «включая» + реиндекс + простои РЖД + недоучёт опор. Подписанный убыток.

Sheet 04_СМР_по_позициям
A1: 04_ПО ПОЗИЦИЯМ СМР/МОНТАЖ — ПАКЕТЫ П-1…П-4
A2: Потолок = сметная стоимость работ по ЛСР (ИИ-подрядчик). Себест и разница (маржа генподряда) — формулы из 02_Параметры по 3 сценариям.
B3: Пакет | C3: Объём работ | D3: Потолок ЛСР ₽ | E3: Себест Опт | F3: Маржа Опт | G3: Себест Норм | H3: Маржа Норм | I3: Себест Пес | J3: Маржа Пес
B4: П-1 | C4: ЭОМ: 133 опоры, фундаменты/анкеры, ГНБ-проколы 3 м, подвеска СИП-4 4,96 км, заземление, малый блок КС (поперечины) | D4: =02_Параметры!D5 -> 24822167 | E4: =02_Параметры!C5*02_Параметры!C11*02_Параметры!C12+02_Параметры!C5*(1-02_Параметры!C11)*(1-02_Параметры!C13) -> 19361290 | F4: =02_Параметры!C5-E4 -> 5460876.7 | G4: =02_Параметры!D5*02_Параметры!D11*02_Параметры!D12+02_Параметры!D5*(1-02_Параметры!D11)*(1-02_Параметры!D13) -> 19609512 | H4: =02_Параметры!D5-G4 -> 5212655.1 | I4: =02_Параметры!E5*02_Параметры!E11*02_Параметры!E12+02_Параметры!E5*(1-02_Параметры!E11)*(1-02_Параметры!E13) -> 23581059 | J4: =02_Параметры!E5-I4 -> 1241108.4
B5: П-2 | C5: СОТ: монтаж 191–202 камер, СКС, ВОЛС, РЛS Orwell-R, 36 коммутаторов, серверы СХД, ИБП (оборуд. давальческое) | D5: =02_Параметры!D6 -> 11086179 | E5: =02_Параметры!C6*(1-02_Параметры!C14) -> 10310146 | F5: =02_Параметры!C6-E5 -> 776032.53 | G5: =02_Параметры!D6*(1-02_Параметры!D14) -> 10421008 | H5: =02_Параметры!D6-G5 -> 665170.74 | I5: =02_Параметры!E6*(1-02_Параметры!E14) -> 10531870 | J5: =02_Параметры!E6-I5 -> 554308.95
B6: П-3 | C6: ПНР СОТ + спецпроверки/специсследования ФСБ (категорир. помещения, ФЗ 5485-1) | D6: =02_Параметры!D7 -> 1245253 | E6: =02_Параметры!C7*(1-02_Параметры!C15) -> 1170537.8 | F6: =02_Параметры!C7-E6 -> 74715.18 | G6: =02_Параметры!D7*(1-02_Параметры!D15) -> 1170537.8 | H6: =02_Параметры!D7-G6 -> 74715.18 | I6: =02_Параметры!E7*(1-02_Параметры!E15) -> 1195442.9 | J6: =02_Параметры!E7-I6 -> 49810.12
B7: Σ | C7: ИТОГО РЕАЛЬНЫЙ ФРОНТ (П-1+П-2+П-3), сценарий Б | D7: =D4+D5+D6 -> 37153599 | E7: =E4+E5+E6 -> 30841975 | F7: =F4+F5+F6 -> 6311624.5 | G7: =G4+G5+G6 -> 31201058 | H7: =H4+H5+H6 -> 5952541 | I7: =I4+I5+I6 -> 35308372 | J7: =J4+J5+J6 -> 1845227.4
B8: П-4 | C8: УСЛОВНО «вынос/возврат КС 27,5 кВ» — ТОЛЬКО если РЖД подтвердит. Не рынок → бригада ЭЧ ЮУЖД в «окна». В выручку/себест НЕ включён (лист 08) | D8: 64710398
B10: КАК ЧИТАТЬ. «Маржа» здесь = потолок ЛСР − себестоимость = вклад пакета в прибыль генподряда. В ОПТИМИСТ/НОРМАЛЬНЫЙ П-1 ЭОМ выполняется СВОИМИ силами (k≈0,78–0,79 от сметы) — забираем НР/СП, маржа ~5 млн. В ПЕССИМИСТ П-1 отдан в 100% субподряд (дисконт 5%) — забираем только ~1,2 млн. Это ГЛАВНЫЙ рычаг маржи объекта: на узком рынке (ФСБ/РЖД) субподряд даёт лишь 5–7% дисконта, а самовыполнение ЭОМ — 18–22%. П-2 СОТ и П-3 ПНР — всегда субподряд (лицензии ФСБ/ФСТЭК), маржа тонкая. Блок КС (П-4) в расчёт НЕ входит — это «воздух» до ответа РЖД (лист 08).

Sheet 05_ТМЦ_реестр
A1: 05_РЕЕСТР ТМЦ НАШЕЙ ПОСТАВКИ — РЫНОК vs СМЕТА (источник: ИИ-снабженец, живые прайсы 03.08.2026)
A2: Материалы в РИМ «зашиты» в позиции (сметная база всего 1,86 млн). Ниже — реальная закупка с логистикой до ст. Зауралье (плечо ~2000 км от Москвы / ~350 км от Екб).
B3: Позиция ТМЦ | C3: Ед. | D3: Объём | E3: Цена мин ₽ | F3: Цена макс ₽ | G3: До объекта мин ₽ | H3: До объекта макс ₽ | I3: Средн. ₽ | J3: Объём | K3: Примечание
B4: A. НАША ПОСТАВКА
B5: СИП-4 4×25 самонесущий | C5: м | D5: 4960 | E5: 110 | F5: 140 | G5: 600160 | H5: 763840 | I5: =(G5+H5)/2 -> 682000 | J5: НАША | K5: Эталон РД: смета=кабельный журнал, Δ0,1%. Кабель.РФ/Энергосфера
B6: ВОК подвесной 8 вол. G.652.D | C6: м | D6: 5000 | E6: 35 | F6: 70 | G6: 192500 | H6: 385000 | I6: =(G6+H6)/2 -> 288750 | J6: НАША | K6: Объём по кабельному журналу РД — уточнить
B7: Труба ПНД ПЭ100 D50 | C7: м | D7: 600 | E7: 90 | F7: 130 | G7: 59400 | H7: 85800 | I7: =(G7+H7)/2 -> 72600 | J7: НАША | K7: Защита кабеля / проколы ГНБ 3 м
B8: Кабель ВВГнг(A)-LS (проводка б/к) | C8: компл | D8: 1 | E8: 80000 | F8: 180000 | G8: 86400 | H8: 194400 | I8: =(G8+H8)/2 -> 140400 | J8: НАША | K8: Внутр. проводка аппаратной
B9: Прокат листовой Ст3 | C9: т | D9: 0.078 | E9: 60000 | F9: 66000 | G9: 5242 | H9: 5766 | I9: =(G9+H9)/2 -> 5504 | J9: НАША | K9: Смета 62 596 ₽/т — в рынке
B10: Анкер ж/б / фунд. блок под опору | C10: шт | D10: 133 | E10: 3500 | F10: 8000 | G10: 502740 | H10: 1149120 | I10: =(G10+H10)/2 -> 825930 | J10: НАША | K10: 1 анкер на опору (ИИ-ГИП: корректно)
B11: Ригель/поперечина П-перехода | C11: шт | D11: 3 | E11: 120000 | F11: 220000 | G11: 381600 | H11: 699600 | I11: =(G11+H11)/2 -> 540600 | J11: НАША | K11: Единств. обоснованное место работ у КС
B12: Плита дорожная ПДН 6×2 (под б/к) | C12: шт | D12: 3 | E12: 18000 | F12: 28000 | G12: 59400 | H12: 92400 | I12: =(G12+H12)/2 -> 75900 | J12: НАША | K12: 5,04 м³. Завод Екб
B13: Блок-контейнер сев. исп. 6×2,4 | C13: шт | D13: 1 | E13: 180000 | F13: 350000 | G13: 201600 | H13: 392000 | I13: =(G13+H13)/2 -> 296800 | J13: НАША | K13: ИИ-ГИП: чертёж 2 vs смета 1 — свести. −40°C
B14: Комплект заземления (полоса, клеммы 130, верт. 5) | C14: компл | D14: 1 | E14: 150000 | F14: 350000 | G14: 165000 | H14: 385000 | I14: =(G14+H14)/2 -> 275000 | J14: НАША | K14: Противоречие РД (штыри vs УКЗУ) — уточнить
B15: Молниезащита/ОПН высоких опор у КС | C15: компл | D15: 1 | E15: 100000 | F15: 250000 | G15: 110000 | H15: 275000 | I15: =(G15+H15)/2 -> 192500 | J15: НАША | K15: ИИ-ГИП: в РД НЕ отражена — резерв
B16: Арматура крепления СИП (на 133 опоры) | C16: компл | D16: 133 | E16: 1500 | F16: 3500 | G16: 215460 | H16: 502740 | I16: =(G16+H16)/2 -> 359100 | J16: НАША | K16: Часть может быть «зашита» в расценке СИП
... B19: Криптошлюз ViPNet Coordinator HW | C19: компл | D19: 1 | E19: 1200000 | F19: 1600000 | G19: 1236000 | H19: 1648000 | I19: =(G19+H19)/2 -> 1442000 | J19: НАША-СКЗИ | K19: Смета 1 386 845. Только партнёр ИнфоТеКС
B20: B. ОБЪЁМ ПОД ВОПРОСОМ (опоры)
B21: Опора металл. ≤0,6 т | C21: шт | D21: 127 | E21: 35000 | F21: 52000 | G21: 4711700 | H21: 7000240 | I21: =(G21+H21)/2 -> 5855970 | J21: УТОЧНИТЬ | K21: 🔴 наша/давальческое? Заводы Екб
B22: Опора металл. усиленная 0,6–1 т | C22: шт | D22: 6 | E22: 55000 | F22: 85000 | G22: 349800 | H22: 540600 | I22: =(G22+H22)/2 -> 445200 | J22: УТОЧНИТЬ | K22: 🔴 под ригели. Тот же объём-вопрос
B23: C. ДАВАЛЬЧЕСКОЕ (вне нашей поставки)
B24: «Железо» СОТ: 202 камеры, 2×СХД, 8×РЛС, 8×НЕО, 36 коммут., ИБП | C24: компл | D24: 1 | E24: 15810000 | F24: 45600000 | G24: 15810000 | H24: 45600000 | I24: =(G24+H24)/2 -> 30705000 | J24: ДАВАЛЬЧ. | K24: 🔴 поставка заказчика (контур ФСБ). Себест для нас = 0
B25: ИТОГО НАША ПОСТАВКА (без опор/железа), средн. | I25: =SUM(I5:I19) -> 5315884
B27: ВЫВОД ИИ-ЭКОНОМИСТА ПО ТМЦ. Наша поставка (материалы ЭОМ + климатика + ViPNet), средняя с логистикой ≈ 5,3 млн — примерно паритет со сметной компенсацией (материалы 1,86 + оборуд 2,22 = 4,08 млн) + региональная экономия Урал (+0,3–0,6 млн). КЛЮЧ — два объём-вопроса, а не цена: (1) МЕТАЛЛ ОПОР 5–7,5 млн — если недоучтён и наш, прямой минус к марже; (2) «ЖЕЛЕЗО» СОТ 15,8–45,6 млн — почти наверняка давальческое (контур ФСБ). Если вдруг наше — объект глубоко убыточен без допсметы. До письменного разграничения объёма (ИИ-договорник) себестоимость ТМЦ недостоверна. В финансовый результат (лист 03) заложен паритет по ТМЦ нашей поставки; риск опор — в строке «ТМЦ недобор» пессимиста.

Sheet 06_АХР_генподряд
A1: 06_АХР ГЕНПОДРЯДЧИКА — ШТАТ НА ОБЪЕКТ (зона ИИ-экономиста — коллеги не считали)
A2: Штат, который РЕАЛЬНО нужен генподряду на слаботочку+электрику на действ. ж/д под режимом ФСБ. Активная фаза 6 мес. ПТО/ИД-инженер — в стоимости ИД (лист 07), здесь НЕ дублируется.
B3: Активная фаза (мес) — управляющая ячейка | C3: 6 | D3: Срок в документах не задан (флаг ИИ-руководителя проекта). Принято 6 мес (ИИ-ПТО оценивал 5). «Окна» РЖД растягивают график.
B5: Роль в генподряде | C5: Ставка ₽/мес | D5: Загрузка | E5: Мес | F5: ФОТ ₽ | G5: Обоснование
B6: Руководитель проекта / нач. участка | C6: 180000 | D6: 0.5 | E6: =$C$3 -> 6 | F6: =C6*D6*E6 -> 540000 | G6: РП, решения, отношения с заказчиком/РЖД. Распределён между объектами
B7: Производитель работ (прораб), вахта | C7: 140000 | D7: 1 | E7: =$C$3 -> 6 | F7: =C7*D7*E7 -> 840000 | G7: Постоянно на объекте: координация субподряда, приёмка, наряды-допуски
B8: Инженер ОТ и ТБ + допуски РЖД/режим ФСБ | C8: 110000 | D8: 0.5 | E8: =$C$3 -> 6 | F8: =C8*D8*E8 -> 330000 | G8: Наряды-допуски, «окна», ПОТ ЭЭУ, режимные допуски категорир. объекта
B9: Инженер по снабжению / логистике | C9: 90000 | D9: 0.4 | E9: =$C$3 -> 6 | F9: =C9*D9*E9 -> 216000 | G9: ТМЦ до ст. Зауралье (плечо 2000 км), давальческое от заказчика
B10: Экономист / оформление КС-2, КС-3 | C10: 100000 | D10: 0.3 | E10: =$C$3 -> 6 | F10: =C10*D10*E10 -> 180000 | G10: Актирование, сходимость, недопуск блока КС в акты (с ИИ-ПТО)
B11: ИТОГО ФОТ штата ГП | F11: =SUM(F6:F10) -> 2106000
B12: Страховые взносы (~30% на ФОТ) | F12: =F11*0.3 -> 631800 | G12: Тариф взносов ~30%
B13: Вахта/командировки (проживание, проезд, суточные) | F13: =500000 -> 500000 | G13: Объект 2000 км от центра; 2–3 чел вахтой 6 мес
B14: Офис/связь/ПО (ГРАНД-Смета, ЭДО ИД)/транспорт | F14: =400000 -> 400000 | G14: Оргтехника, ПО, аренда авто на объекте
B15: ИТОГО АХР ГЕНПОДРЯДА (НОРМАЛЬНЫЙ), ₽ | F15: =F11+SUM(F12:F14) -> 3637800
B17: СВЯЗЬ С финансовый результат. Этот итог (нормальный) подставлен в 02_Параметры → АХР. Оптимист = ×0,75 (лидер распределён, короче срок, меньше вахты). Пессимист = ×1,30 (растянутый график из-за «окон» РЖД, полная вахта). ВАЖНО: сметные накладные расходы (НР) 26,96 млн формально должны покрывать АХР — НО на этом объекте почти весь НР «сидит» в цене субподряда (субподрядчик держит свой НР). Наш генподрядный АХР ~3,6 млн — это РЕАЛЬНЫЙ денежные средства-расход, который покрывается только дисконтом + сметной прибылью. Именно он съедает тонкую маржу — коллеги его не учли.

Sheet 07_Стоимость_ИД
A1: 07_СТОИМОСТЬ ПРОИЗВОДСТВА ИД — ПО ПОЗИЦИЯМ (источник: ИИ-ПТО, ПТО)
A2: Что реально стоит «сделать ИД» на объекте под ж/д + режим ФСБ. Ключ: что НЕ выделено в смете и давит на маржу.
B3: Компонент производства ИД | C3: Кол-во/ед | D3: Ставка ₽ | E3: Сумма ₽ | F3: В смете? | G3: Примечание
B4: A. Своими силами (труд ПТО/ИД)
B5: ПТО/ИД-инженер (реестр ИД, АОСР, журналы) | C5: 5 чел·мес | D5: 130000 | E5: 650000 | F5: в НР | G5: Не дублируется с АХР (лист 06 без ПТО)
B6: Инженер-геодезист (исполнит. съёмки опор/ГНБ/плит) | C6: 1 компл | D6: 200000 | E6: 200000 | F6: ⚠ част. | G6: Привлечённая организация/свой — уточнить
B7: B. Привлечённые услуги
B8: Аккредит. электролаборатория (ЭТЛ) | C8: 1 компл | D8: 300000 | E8: 300000 | F8: 🔴 НЕТ | G8: Изоляция, петля фаза-ноль, ЗУ, СИП. Условие старта
B9: Оптические измерения ВОЛС (рефлектометрия) | C9: 1 компл | D9: 120000 | E9: 120000 | F9: 🔴 НЕТ | G9: Паспорт ВОЛС по одномод. ВОК СОТ
B10: Спецпроверки/специсследования ФСБ (СП и СИ) | C10: 1 компл | D10: 354583 | E10: 354583 | F10: ✅ Гл.9 | G10: В СМЕТЕ (ЛСР 09-02) — НЕ сверх сметы
B11: Аттестация объекта информатизации (ФСТЭК-77) | C11: 1 компл | D11: 300000 | E11: 300000 | F11: 🟨 ? | G11: ОБЪЁМ ПОД ВОПРОСОМ: наш или заказчик
B12: C. Электронная ИД + комплектация
B13: Электронная ИД (ГОСТ Р 70108-2025): XML, ЭЦП | C13: 1 компл | D13: 150000 | E13: 150000 | F13: 🟨 ? | G13: Часто система заказчика
B14: Комплектация ИД (печать, сшивка, копии) | C14: 1 компл | D14: 60000 | E14: 60000 | F14: ⚠ част. | G14: Число экз — из договора
B15: ИТОГО производство ИД (всё, вкл. в смете) | E15: =SUM(E5:E14) -> 2134583
B16: из них УЖЕ В СМЕТЕ (СП и СИ, Гл.9) | E16: 354583
B17: СВЕРХ СМЕТЫ — не выделено в ЛСР (🔴 съедает маржу) | E17: =E15-354583 -> 1780000
B19: СВЯЗЬ С финансовый результат. «Сверх сметы» ≈ 1,78 млн (нормальный) подставлено в 02_Параметры → ИД сверх сметы. Оптимист 1,50 млн (аттестация ФСТЭК давальческая, электронная ИД — система заказчика). Пессимист 2,13 млн (аттестация ФСТЭК наша). Это 4,8% реального фронта — ориентир ИД для слаботочки+электрики под режимом 3–6%, в норме, но на объекте у красной линии 5% — прямое давление на прибыль.

Sheet 08_Блок_КС_риск
A1: 08_БЛОК «ВЫНОС/ВОЗВРАТ КС» 64,71 млн — ГЛАВНЫЙ РИСК ОБЪЕКТА
A2: ИИ-ГИП+ИИ-сметчик вернули ВОР: 200 км в смете при физике ~17 км (кратность 11×). На КС-2 закрыть нельзя. Разбор 3 судеб.
A3: ДЕНЕЖНЫЙ ВЕС БЛОКА (из ЛСР ЭОМ, ИИ-сметчик лист 05)
B4: Показатель | C4: Сумма ₽ | D4: Комментарий
B5: Итого большой блок «вынос КС» (198 км) | C5: =64710398 -> 64710398 | D5: 🔴 «воздух» до ответа РЖД
B6: в т.ч. НР на блоке КС | C6: =16257460 -> 16257460 | D6: пр.812/пр
B7: в т.ч. СП на блоке КС | C7: =7700902 -> 7700902 | D7: пр.774/пр
B8: Малый блок (поперечины П-перехода) — ОБОСНОВАН | C8: =1309729 -> 1309729 | D8: ✅ в реальном фронте П-1
B9: Заземление опор — ОБОСНОВАНО | C9: =648489 -> 648489 | D9: ✅ не часть выноса
A11: ТРИ СУДЬБЫ БЛОКА КС (знак маржи объекта определяет именно это)
B12: Сценарий судьбы КС | C12: А. РЖД подтвердил вынос | D12: Б. Объём снят (аудит Гл.12) | E12: В. Тверд. цена, не делаем | F12: Комментарий ИИ-экономиста
B13: Собираемая выручка блока КС, ₽ | C13: 64710398 | D13: 0 | E13: 0 | F13: В: деньги за невыполненный вынос НЕ поступят
B14: Реальная себест. выноса (окна ЭЧ РЖД), ₽ | C14: -60000000 | D14: 0 | E14: 0 | F14: А: реальная работа бригадой ЭЧ + простои
B15: Маржа на блоке КС, ₽ | C15: =C13+C14 -> 4710398 | D15: =D13+D14 -> 0 | E15: =E13+E14 -> 0 | F15: А: тонкая, риск простоев; Б: нейтрально; В: минус
B16: Влияние на объект | C16: риск простоев | D16: БАЗОВЫЙ | E16: убыток −5,3 млн | F16: Строим по Б (консенсус конвейера)
B18: ВЫВОД ИИ-ЭКОНОМИСТА. Блок КС — не «жирок», а бомба. В моём финансовый результат (лист 03) он ИСКЛЮЧЁН из выручки и себестоимости — считаю по сценарию Б (весь конвейер согласен). Категорически нельзя строить финмодель на блоке КС как на выручке: (1) физически 200 км нет; (2) работать на КС 27,5 кВ вправе только ЭЧ РЖД; (3) невыполненный вынос нельзя актировать в КС-2 → сценарий В = −5,3 млн + риск фиктивных актов (ст.159 УК, флаг ИИ-договорника). Действие ИИ-руководителя проекта: официальный запрос в РЖД/Заказчику о фактически требуемом выносе + чистка блока из НМЦК через ценовой аудит Гл.12 ДО подписания.

Sheet 09_Сквозные_вычеты
A1: 09_СКВОЗНЫЕ ВЫЧЕТЫ И ФИНУСЛОВИЯ
A2: Факторы, которые не привязаны к конкретной позиции, но меняют финрезультат. Каждый — в рублях (Протокол 3).
A3: 1. НДС 20% → 22% (ФЗ №425-ФЗ от 28.11.2025) — флаг 1
B4: Гл.1-9 без НДС (база) | C4: 107076237 | D4: ССРСС / ИИ-сметчик
B5: НДС в смете (20%) | C5: =107076237*0.2 -> 21415247 | D5: смета в старой ставке
B6: НДС фактический (22%, работы 2026) | C6: =107076237*0.22 -> 23556772 | D6: ФЗ 425-ФЗ
B7: НЕДОБОР при цене «включая НДС 20%» | C7: =107076237*0.02 -> 2141524.7 | D7: ≈2,14 млн — съедает подрядчик
B8: ПОЗИЦИЯ (ИИ-договорник): договора нет → заходим с формулой «Цена работ ___, кроме того НДС по ставке на дату реализации». НДС «сверху» → рост ставки на заказчике, риск 2,14 млн снят. В финансовый результат: оптимист/нормальный = 0, пессимист = 2,14 млн.
A10: 2. Двойной счёт ПНР (ИИ-сметчик лист 04)
B11: ПНР дублирована: строка в ЛСР СОТ = отдельный ЛСР 09-01 | C11: 890670 | D11: Воздух в НМЦК; с непредв+НДС ≈ 1,09 млн. Снимается ст.94 44-ФЗ. В выручку Б НЕ включён.
A13: 3. Реиндекс II кв.2025 → 2026 (ИИ-сметчик лист 08) — флаг 7
B14: База СМР+монтаж без НДС (II кв.2025) | C14: 100630000 | D14: Дефлятор СМР ~5%/год. Удорожание себест. ~5,0 млн на полном объёме; на реальном фронте ~0,5–1,5 млн. Компенсируется индексацией контракта — если прописано.
A16: 4. Обеспечение: БГ vs ГУ + аванс (ИИ-договорник лист 07)
B17: НМЦК (база обеспечения) | C17: 128491484 | D17: с НДС
B18: Гарантийное удержание 5% (вне оборота) | C18: =128491484*0.05 -> 6424574.2 | D18: ≈6,42 млн заморожено
B19: Стоимость БГ (1,5%/год × 1,5 года) | C19: =128491484*0.05*0.015*1.5/0.05 -> 2891058.4 | D19: комиссия банка
B20: Эффект замены ГУ→БГ (высвобождение − комиссия) | C20: =128491484*0.05-128491484*0.05*0.015*1.5 -> 6280021.3 | D20: ≈3,53 млн высвобождено
B21: Аванс критичен для кассы: при отсутствии аванса и оплата субподрядчику после оплаты заказчиком с субподрядом — кассовый разрыв. ИИ-договорник: добиваться max аванса + БГ вместо ГУ.
A23: 5. 🔴 РЕЖИМ ГОЗ / 275-ФЗ (новый флаг ИИ-договорника) — критично для финмодели
B24: Заказчик — интересант ПУ ФСБ (погранпункт, гостайна). Высокая вероятность ГОЗ (275-ФЗ) или закрытой закупки. Это МЕНЯЕТ ВСЮ ФИНМОДЕЛЬ: (1) отдельный счёт в уполномоченном банке + банковское/казначейское сопровождение; (2) РАЗДЕЛЬНЫЙ УЧЁТ по каждому контракту; (3) ПРАВИЛО РЕНТАБЕЛЬНОСТИ «1% + 20%» — прибыль ограничена 1% привнесённых затрат (субподряд/ТМЦ) + 20% собственных затрат; (4) лицензии ФСБ/ФСТЭК. На тонкой марже правило «1%+20%» скорее НЕ ограничивает (мы ниже потолка), но раздельный учёт и уполномоченный банк резко усложняют движение денежных средств и удорожают админ. ДЕЙСТВИЕ: ИИ-договорник — установить режим закупки ДО подписания; я пересчитаю финмодель под ГОЗ, если подтвердится.

Sheet 10_Передачи_смежникам
A1: 10_ПЕРЕДАЧИ СМЕЖНИКАМ + ФИНАНСОВЫЙ АЛЕРТ ИИ-РУКОВОДИТЕЛЮ ПРОЕКТА
A2: 🚨 ФИНАНСОВЫЙ АЛЕРТ | 03.08.2026 | ЖДПП «Зауралье»
A3: СИТУАЦИЯ: свёл себестоимость по всему конвейеру. Валовая оценка коллег (+14%) не выдерживает вычета реальной цены субподряда + АХР генподряда + ИД. ЦИФРЫ: базовый сценарий −0,26 млн (−0,6%), НИЖЕ красной линии 5%. Оптимист +2,79 млн (+7,0%, самовыполнение ЭОМ), пессимист −10,95 млн (−27%). ВАРИАНТЫ: (1) не подавать до разрешения блока КС/объёма/НДС — рекомендую; (2) подавать только с самовыполнением ЭОМ + «НДС сверху» + давальческим оборуд.; (3) отказ, если заказчик держит блок КС или навязывает поставку железа. РЕКОМЕНДУЮ вариант 1. НУЖНО РЕШЕНИЕ ИИ-РУКОВОДИТЕЛЯ ПРОЕКТА до подачи на закупку.
A8: ЧТО НЕСУ ДАЛЬШЕ ПО КОНВЕЙЕРУ
B9: Кому | C9: Задача с денежным эффектом
B10: → ИИ-руководителю проекта (РП) | C10: Заключение: базовый сценарий у красной линии (−0,6%). Брать только при 3 условиях (лист 00). Прибыль концентрируется на самовыполнении ЭОМ — держать этот пакет своими силами, не отдавать в дорогой субподряд.
B11: → ИИ-договорнику (Договор) | C11: КРИТ: (1) НДС «сверху» (−2,14 млн риска); (2) установить режим ГОЗ/275-ФЗ — меняет мою финмодель (уполномоченный банк, «1%+20%»); (3) объём оборуд./опор — давальческое письменно; (4) аванс max + БГ вместо ГУ (+3,53 млн оборотки); (5) чистка блока КС из НМЦК.
B12: → ИИ-сметчику (Смета) | C12: Подтверждаю: реальный фронт 37,15 млн, блок КС 64,71 млн — воздух. Прошу пересчёт ВОР на дату работ 2026 (реиндекс ~5%) и точную раскладку НР/СП на реальном фронте — от неё зависит выгода самовыполнения ЭОМ.
B13: → ИИ-снабженцу (Снаб) | C13: Держу ТМЦ нашей поставки паритетом (~5,3 млн). Жду 3 КП по СИП-4, ВОК, опорам с логистикой до ст. Зауралье. Критично: письменный статус объёма «железа» СОТ и металла опор — от этого знак маржи.
B14: → ИИ-подрядчику (Подряд) | C14: Потолки переданы (лист 04): П-1 ЭОМ 24,82 (рассматриваем самовыполнение!), П-2 СОТ 11,09 (субподряд, лицензиат ФСБ), П-3 1,25. Дисконт 6% = +2,23 млн — критический рычаг. Спецтехника — аренда Курган (подтверждаю).
B15: → ИИ-ПТО (ПТО) | C15: Стоимость ИД сверх сметы 1,78 млн заложил в себестоимость явно (не в НР). Держи недопуск блока КС в АОСР/КС-2. Уточни объём аттестации ФСТЭК — двигает цифру ИД на ±0,3 млн.
B16: → ИИ-администратору (Админ) | C16: В реестр: статус себеса — 🔴/🟡 (маржа у красной линии). 3 блокирующих условия с ответственными. Следующий шаг ИИ-экономиста — БДДС после получения договора (аванс, график).
A18: ИИ-экономист · СтройИнтеллект.Эконом v8.2 · 03.08.2026. Точность ±15% (нет договора и РД). Финмодель БДДС — Такт 2 после договора. «Лучше показать убыток сейчас, чем встретить через 6 месяцев.»
