Workbook

Sheet 00_О_базе
A1: ОПОРНАЯ БАЗА ГЕНПОДРЯДА РФ · v1.0 — движок расчёта агента «Прохорыч» (СтройИнтеллект)
A3: Назначение | B3: База знаний для предпроектной и текущей оценки объектов генподряда. Каждая цифра — с источником, датой и статусом. Приоритет: промт > эта база > эталон Йошкар-Ола > веб > знания модели.
A4: Заказчик решения | B4: АО «МОДЦ» (ИНН 5024185328), дорожно-строительный генподряд, Московская обл.
A5: Источник наполнения v1 | B5: Полный прогон ОСК г. Йошкар-Ола, 2 этап (НМЦК 4 002 854 177 ₽ с НДС 22%, 44-ФЗ, 36 мес). Приложения 1–4 + данные + ГПР.
A6: Дата сборки | B6: 22.07.2026
A7: Правило статуса | B7: ✅ ФАКТ (источник+дата+действует) · ⚠ ПРЕДПОЛОЖЕНИЕ (оценка) · ❌ НЕИЗВЕСТНОЕ (нужны данные). Всё старше 90 дней → ⚠ проверить.
A8: Цвет ячеек | B8: СИНИЙ = вход/лёвер (менять можно) · ЧЁРНЫЙ = формула/факт · ЗЕЛЁНЫЙ = ссылка на другой лист · ЖЁЛТАЯ заливка = ключевое допущение / заполнить.
A9: Домены (слоты 13.x) | B9: 13.1 Дороги/ИССО (каркас) · 13.2 ВКХ/очистные (НАПОЛНЕН Йошкар-Олой) · 13.3 Сети/ИТП · 13.4 Промонтаж · 13.5 Общестрой/КЖ · 13.6 Энергетика · 13.7 Благоустройство.
A11: КАРТА ЛИСТОВ
A12: Лист | B12: Что внутри
A13: 1. Прайс работ | B13: Rate card СМР по видам (земля/КЖ/монтаж/сети/дорога/ИССО), коэф. рыночности по регионам
A14: 2. Материалы | B14: Металл, бетон/ЖБИ, трубы, кабель, инертные, битум/ПБВ, геосинтетика — цена, дата, плечо
A15: 3. Оборудование-длинноцикл | B15: Ядро по доменам: цена, импорт/РФ-аналог, лид-тайм, пометка «под КП»
A16: 4. Ставки труда | B16: Оклады ИТР и рабочих (мес с налогами) по ролям, +вахта
A17: 5. Нормативы выработки | B17: Чел-ч/ед, коэффициенты (положение/толщина/температура)
A18: 6. Юнит-экономика | B18: Структура себестоимости и косвенных генподряда, наценки, движок P&L→EBT
A19: 7. Алгоритмы | B19: Все формулы движка (ФОТ, сроки, сведение цены, деньги во времени)
A20: 8. Нормбаза | B20: Документ → статус «действует/отменён» → актуальный аналог
A21: 9. Реестр объектов | B21: Провенанс цифр (Йошкар-Ола и далее)
A22: 10. Уроки | B22: Вшитые уроки предыдущих объектов
A23: 11. Сверка расчёт-факт | B23: Заготовка под сверку оценки с пришедшими КП/счетами
... A31: 13.7 Благоустройство | B31: Доменный слот (каркас)

Sheet Параметры_объект
A1: ПАРАМЕТРЫ ОБЪЕКТА — управляющий лист (синие ячейки = входы) · пример: ОСК Йошкар-Ола
B3: Легенда: синие ячейки (C) — редактируемые входы; меняешь → пересчёт по листам 6/7. Значения ниже — пример Йошкар-Олы.
A5: 1. ОБЩИЕ ПАРАМЕТРЫ КОНТРАКТА
A6: # | B6: Параметр | C6: Значение | D6: Ед. | E6: Источник / статус
A7: 1 | B7: НМЦК с НДС (выручка заказчика) | C7: 4002854177 | D7: ₽ | E7: ✅ Конкурс 0108500000426003927, ЕИС
A8: 2 | B8: Ставка НДС | C8: 0.22 | D8: доля | E8: ✅ 2026 г.
A9: 3 | B9: Срок строительства | C9: 36 | D9: мес | E9: ✅ договор; ПОС 35,7≈36; норматив СНиП ≈30
A10: 4 | B10: Налог на прибыль | C10: 0.25 | D10: доля | E10: ✅ 25% с 2025 (НК РФ)
A11: 5 | B11: Гарантийное удержание (ГУ) | C11: 0.05 | D11: доля | E11: ✅ договор 4.12
A12: 6 | B12: Аванс от заказчика | C12: 0.2955 | D12: доля | E12: ✅ договор 2.8, гасится с каждого КС
A13: 7 | B13: ОПР/ОХР холдинга | C13: 0.02 | D13: доля | E13: ⚠ % от выручки без НДС
A14: 8 | B14: Ставка капитала (кредит/овердрафт) | C14: 0.2 | D14: год | E14: ⚠ для стоимости разрывов и ГУ
A16: 2. СЕБЕСТОИМОСТЬ ПО СЛОЯМ (входы для финмодели)
A17: # | B17: Слой себестоимости | C17: Себест., ₽ | D17: Ед. | E17: Дельта к НМЦК / статус
A18: 1 | B18: Материалы (рынок 2026) | C18: 177950820 | D18: ₽ | E18: +242 млн, ✅ рынок ПФО (без НДС)
A19: 2 | B19: Оборудование стандартное (−8%) | C19: 523852459 | D19: ₽ | E19: +55,6 млн, ⚠ оценка (без НДС)
A20: 3 | B20: Оборудование ИМПОРТНОЕ ЯДРО ТОП-20 | C20: 1999754098 | D20: ₽ | E20: 🔴 P=НМЦК-доля, дельта 0 · КП НЕТ (без НДС)
A21: 4 | B21: СМР (работы+монтаж+ПНР+перевозки) | C21: 277868852 | D21: ₽ | E21: +70,2 млн, ⚠ коэф.рыночн. (без НДС)
B22: Косвенные генподряда за срок (АХР/ВЗиС/городок/ИТР) — см. лист «6. Юнит-экономика»

Sheet 1_Прайс_работ
A1: 1 · ПРАЙС РАБОТ И КОЭФФИЦИЕНТ РЫНОЧНОСТИ СМР (коэф = рынок/смета; <1 → маржа генподряда)
A3: Источник: Подрядный фон ОСК Йошкар-Ола (регион Марий Эл — дешёвый по труду). Коэф ⚠ калибровать под регион/профиль. Дельта = НМЦК×(1−коэф).
A5: Ключ ФЕР | B5: Группа работ | C5: Коэф рын. | D5: Логика / регион | E5: Позиций | F5: НМЦК, ₽ | G5: Дельта, ₽
A6: ФЕР01 | B6: Земляные работы | C6: 0.8 | D6: Массовый фронт, своя техника, дешёвый труд | E6: 328 | F6: 18744555 | G6: =F6*(1-C6) -> 3748911
A7: ФЕР05 | B7: Свайные работы | C7: 0.87 | D7: Узкий фронт: техника из Казани | E7: 25 | F7: 24944374 | G7: =F7*(1-C7) -> 3242768.6
A8: ФЕР06 | B8: Бетон/ж-б монолитные | C8: 0.8 | D8: Много местных бригад, конкурентно | E8: 219 | F8: 17850248 | G8: =F8*(1-C8) -> 3570049.6
A9: ФЕР07 | B9: Сборные ж-б конструкции | C9: 0.83 | D9: Монтаж сборного ж/б | E9: 62 | F9: 1352500 | G9: =F9*(1-C9) -> 229925
A10: ФЕР08 | B10: Кирпич / блоки | C10: 0.82 | D10: Каменные работы, конкурентно | E10: 45 | F10: 1923968 | G10: =F10*(1-C10) -> 346314.24
A11: ФЕР09 | B11: Металлоконструкции | C11: 0.83 | D11: Изготовление/монтаж МК | E11: 181 | F11: 7410533 | G11: =F11*(1-C11) -> 1259790.6
A12: ФЕР10 | B12: Деревянные конструкции | C12: 0.83 | D12: Средняя маржа | E12: 49 | F12: 1082955 | G12: =F12*(1-C12) -> 184102.35
A13: ФЕР11 | B13: Полы | C13: 0.83 | D13: Конкурентный фронт | E13: 137 | F13: 4642822 | G13: =F13*(1-C13) -> 789279.74
A14: Монтаж | B14: Монтаж технол. оборуд./трубопроводов | C14: 0.88 | D14: Узкий фронт — дисконт минимален | E14: 1037 | F14: 43880000 | G14: =F14*(1-C14) -> 5265600
A15: ФЕРп | B15: ПНР (пусконаладка) | C15: 0.9 | D15: Очень узкий фронт, мало исполнителей | E15: 404 | F15: 34710000 | G15: =F15*(1-C15) -> 3471000
A16: Перевозка | B16: Погрузка/перевозка грунта и мусора | C16: 0.85 | D16: Местные перевозчики | E16: 118 | F16: 34824000 | G16: =F16*(1-C16) -> 5223600
B17: ИТОГО (выборка) | E17: =SUM(E6:E16) -> 2605 | F17: =SUM(F6:F16) -> 191365955 | G17: =SUM(G6:G16) -> 27331341
A19: Полный СМР-фронт ОСК: 4 626 позиций, НМЦК 409,4 млн ₽, суммарная дельта +70,2 млн (17,2%). Коэф рыночности ориентир 0,80–0,92.

Sheet 2_Материалы
A1: 2 · МАТЕРИАЛЫ — рынок vs смета (k рынок = рынок/смета). Цена = DDP до склада. Транспортное плечо — отдельно
A3: Источник: Приложение 2 ОСК Йошкар-Ола (рынок 2026, радиус +500 км: Чебоксары ~90, Казань ~150 км). Металл/бетон дешевле базы 2023.
A5: Материал (якорь) | B5: Ед. | C5: Рынок 2026 (DDP) | D5: Смета 2 кв.2023 | E5: k рынок | F5: Дата | G5: Статус
A6: Песок строительный | B6: м³ | C6: 600 | D6: 800 | E6: =IFERROR(C6/D6,"") -> 0.75 | F6: 06.2026 | G6: ✅ рынок ПФО
A7: Бетон В25 (гидротехн. W6/F200) | B7: м³ | C7: 4050 | D7: 7400 | E7: =IFERROR(C7/D7,"") -> 0.5472973 | F7: 06.2026 | G7: ✅ рынок ПФО
A8: Арматура А500С | B8: т | C8: 52500 | D8: 82700 | E8: =IFERROR(C8/D8,"") -> 0.63482467 | F8: 06.2026 | G8: ✅ рынок ПФО
A9: Кабель АСБл силовой | B9: км | C9: ≈ рынок | D9: выше рынка | E9: — | F9: 06.2026 | G9: ⚠ проверить
A10: Минплита Rockwool | B10: м³ | C10: 10500 | D10: 9500 | E10: =IFERROR(C10/D10,"") -> 1.1052632 | F10: 06.2026 | G10: ✅
A11: Щебень фр. 20-40 | B11: м³ | C11: под КП | D11: — | E11: — | F11: — | G11: ❌ нужен КП+плечо
A12: Битум дорожный БНД | B12: т | C12: под КП 🔴 | D12: — | E12: — | F12: — | G12: ❌ КП — волатильность!
A14: Дельта материалов на объекте: +242 млн (себест. 217,1 vs НМЦК 459,1 млн, 3 672 позиции). Битум для дорог — главный ценовой риск (кейс Каранайаул +158%).

Sheet 3_Оборуд_длинноцикл
A1: 3 · ОБОРУДОВАНИЕ-ДЛИННОЦИКЛ (ЯДРО ЗАТРАТ) — всегда «под КП». Топ-концентрации по объекту
A3: Импортное ядро ТОП-20 ОСК = 2,44 млрд (61% НМЦК, 78% оборуд.). Цену в себестоимость берём ТОЛЬКО из свежего КП. Лид-тайм фильтр/УФ 16–24 нед.
A5: Позиция | B5: Ед. | C5: Кол | D5: НМЦК, ₽ | E5: Импорт (бренд) | F5: РФ-аналог | G5: Лид-тайм | H5: Статус
A6: Дисковый фильтр третичной очистки | B6: шт | C6: 9 | D6: 785183251 | E6: Alfa Laval / Hydrotech | F6: Экополимер, ИнСфера (сито TR) | G6: 16–24 нед | H6: 🔴 под КП+пилот
A7: УФ-станция обеззараживания | B7: компл | C7: 1 | D7: 666886571 | E7: Импорт. УФ-модули | F7: НПО ЛИТ (УДВ), Мелитта, ВОДГЕО | G7: 16–24 нед | H7: 🔴 под КП+пилот
A8: Насос осевой пропеллерный Р-420 | B8: шт | C8: 3 | D8: 138595780 | E8: Flygt (Xylem) | F8: ГМС Ливгидромаш, ЭНА | G8: 10–16 нед | H8: 🔴 под КП
A9: ШУ 35TCP | B9: шт | C9: 2 | D9: 130876059 | E9: импорт | F9: РФ шкафы управления | G9: 8–12 нед | H9: 🔴 под КП
A10: Отстойник комплектной поставки | B10: шт | C10: 2 | D10: 91166022 | E10: импорт | F10: ИнСфера, Аргель | G10: 12–20 нед | H10: 🔴 под КП
A11: Отстойник комплектной поставки (2) | B11: шт | C11: 2 | D11: 77587538 | E11: импорт | F11: ИнСфера, Аргель | G11: 12–20 нед | H11: 🔴 под КП
A12: Блочно-модульная котельная | B12: шт | C12: 1 | D12: 76733831 | E12: стандарт | F12: РФ БМК | G12: 10–14 нед | H12: 🟡 под КП
A13: Скребковая система песколовки | B13: шт | C13: 3 | D13: 61047576 | E13: Finnchain | F13: ИнСфера KURP (прямой) | G13: 8–12 нед | H13: 🟡 под КП
A14: Решётка тонкой очистки | B14: шт | C14: 3 | D14: 42903068 | E14: Finnchain | F14: ИнСфера Hydrig SR (прямой) | G14: 8–12 нед | H14: 🟡 под КП
A15: КТП 1000 кВА | B15: компл | C15: 1 | D15: 42814800 | E15: стандарт | F15: Электрощит-Самара, КЭАЗ | G15: 8–10 нед | H15: 🟢 под КП
A16: Насос центробежный погружной Р-920 | B16: шт | C16: 3 | D16: 37038963 | E16: Flygt | F16: ГМС, ЭНА | G16: 10–16 нед | H16: 🔴 под КП
A17: ИТОГО топ-11 (из 20) | D17: =SUM(D6:D16) -> 2150833459

Sheet 4_Ставки_труда
A1: 4 · СТАВКИ ТРУДА — ИТР и рабочие генподряда (₽/мес с налогами). Пример: штат ГП ОСК (19 ИТР)
A3: Источник: АХР_Городок ОСК. Ставка = оклад×1,44 (страховые). Вахта/командировочные — отдельной статьёй. ⚠ калибровать под регион и год подачи.
A5: Роль | B5: Кол | C5: ₽/мес с налог. | D5: ФОТ на 36 мес, ₽ | E5: Примечание
A6: Руководитель проекта (РП) | B6: 1 | C6: 450000 | D6: =C6*B6*36 -> 16200000
A7: ГИП / гл. инженер стройки | B7: 1 | C7: 380000 | D7: =C7*B7*36 -> 13680000
A8: Начальник участка (общестрой) | B8: 2 | C8: 220000 | D8: =C8*B8*36 -> 15840000
A9: Начальник участка (сети/технология) | B9: 1 | C9: 220000 | D9: =C9*B9*36 -> 7920000
A10: Производитель работ (прораб) | B10: 3 | C10: 170000 | D10: =C10*B10*36 -> 18360000
A11: Мастер СМР | B11: 2 | C11: 130000 | D11: =C11*B11*36 -> 9360000
A12: Начальник ПТО | B12: 1 | C12: 180000 | D12: =C12*B12*36 -> 6480000
A13: Инженер ПТО | B13: 2 | C13: 120000 | D13: =C13*B13*36 -> 8640000
A14: Геодезист | B14: 1 | C14: 130000 | D14: =C14*B14*36 -> 4680000
A15: Инженер ПОС / координатор | B15: 1 | C15: 150000 | D15: =C15*B15*36 -> 5400000
A16: Инженер снабжения | B16: 1 | C16: 120000 | D16: =C16*B16*36 -> 4320000
A17: Инженер ОТ/ПБ/экология | B17: 1 | C17: 120000 | D17: =C17*B17*36 -> 4320000
... A20: Рабочий свой (электрик/плотник/сварщик НАКС) | B20: 3 | C20: 85000 | D20: =C20*B20*36 -> 9180000
A21: ИТОГО ФОТ на срок | D21: =SUM(D6:D20) -> 131580000
A23: Командировочные (80% штата иногородние): аренда квартир 35 000 ₽/мес (2 чел/кв), суточные 700 ₽/день, заезд домой 6 000 ₽ ×11/год.

Sheet 5_Нормативы_выработки
A1: 5 · НОРМАТИВЫ ВЫРАБОТКИ И КОЭФФИЦИЕНТЫ (⚠ ориентиры, калибровать под объект)
A3: Операция / коэффициент | B3: Значение | C3: Ед. | D3: Источник | E3: Статус
A4: Выработка: тяжёлые МК | B4: 0,8 | C4: т/чел·день | D4: канон монтаж | E4: ⚠
A5: Выработка: вентиляция | B5: 5,0 | C5: т/чел·день | D5: канон монтаж | E5: ⚠
A6: Выработка: электромонтаж | B6: 0,89 | C6: т/чел·день | D6: канон монтаж | E6: ⚠
A7: Выработка: бетон КЖ | B7: 0,65 | C7: м³/чел·день | D7: канон | E7: ⚠
A8: Трудозатраты: трубопровод | B8: ≈10 | C8: чел-ч/т | D8: канон монтаж | E8: ⚠
A9: Трудозатраты: сварка | B9: ≈1 | C9: чел-ч/м шва | D9: канон | E9: ⚠
A10: Коэф. положения (проектное/верт.) | B10: ×1,45 | C10: к горизонту | D10: канон промонтаж | E10: ⚠
A11: Коэф. толщины стенки 33→52 мм (ОПР) | B11: ×1,57 | C11: — | D11: канон промонтаж | E11: ⚠
A12: Коэф. толщины 33→52 мм (электроды) | B12: ×2,56 | C12: — | D12: канон промонтаж | E12: ⚠
A13: Коэф. температуры (ниже −30°C) | B13: до ×1,4 | C13: — | D13: ВСН 416-81 | E13: ⚠
A14: Дни ИТР к производственным | B14: ×1,3 | C14: — | D14: движок | E14: ✅
... A16: Ставка с налогами: сдельные | B16: ×1,2 | C16: — | D16: движок | E16: ✅

Sheet 6_Юнит_экономика
A1: 6 · ЮНИТ-ЭКОНОМИКА — движок P&L генподряда до EBT (тянет входы из «Параметры_объект»)
A3: Себестоимость снизу вверх: прямые слои → GM1 → минус косвенные за срок → минус деньги во времени = EBT. Налог — отдельным слоем. Пример: Йошкар-Ола, база 36 мес.
A5: A. КОСВЕННЫЕ ГЕНПОДРЯДА ЗА СРОК (структура АХР/ВЗиС/городок)
A6: Статья косвенных | B6: Сумма, ₽ | C6: Тип | D6: Комментарий | E6: Доля НМЦК
A7: ВЗиС (ограждение, времянки, дороги, склады) | B7: 23773000 | C7: единовр. | D7: Раздел 1 АХР ОСК | E7: =B7/Параметры_объект!$C$7 -> 0.0059390123
A8: Городок и оргтехника (штаб, бытовки, ПК) | B8: 19155000 | C8: единовр. | D8: Раздел 2 АХР ОСК | E8: =B8/Параметры_объект!$C$7 -> 0.0047853355
A9: ФОТ ИТР (19 чел × 36 мес) | B9: 122400000 | C9: за срок | D9: Раздел 3 → лист 4 | E9: =B9/Параметры_объект!$C$7 -> 0.030578181
A10: Командировочные ИТР (80% иногородние) | B10: 24541200 | C10: за срок | D10: Раздел 4 АХР ОСК | E10: =B10/Параметры_объект!$C$7 -> 0.0061309253
A11: Свои рабочие ГП (3 чел + инструмент) | B11: 10179000 | C11: за срок | D11: Раздел 5 АХР ОСК | E11: =B11/Параметры_объект!$C$7 -> 0.0025429355
A12: Содержание площадки (охрана/ТКО/питание/водопониж.) | B12: 36148000 | C12: помесячно | D12: Раздел 6 АХР ОСК | E12: =B12/Параметры_объект!$C$7 -> 0.0090305563
A13: ИТОГО КОСВЕННЫЕ (АХР+ВЗиС+городок+ИТР) | B13: =SUM(B7:B12) -> 236196200 | E13: =B13/Параметры_объект!$C$7 -> 0.059006946
A15: B. P&L ОБЪЕКТА → EBT (база; входы из «Параметры_объект»)
A16: Показатель | B16: Сумма, ₽ | C16: % НМЦК
A17: НМЦК с НДС | B17: =Параметры_объект!$C$7 -> 4002854177 | C17: =B17/Параметры_объект!$C$7 -> 1
A18: минус НДС к уплате | B18: =-Параметры_объект!$C$7*Параметры_объект!$C$8/(1+Параметры_объект!$C$8) -> -7.2182616e+08 | C18: =B18/Параметры_объект!$C$7 -> -0.18032787
A19: ВЫРУЧКА БЕЗ НДС (рабочая база) | B19: =Параметры_объект!$C$7/(1+Параметры_объект!$C$8) -> 3.281028e+09 | C19: =B19/Параметры_объект!$C$7 -> 0.81967213
A20: − Материалы (рынок) | B20: =-Параметры_объект!$C$18 -> -177950820 | C20: =B20/Параметры_объект!$C$7 -> -0.044455984
A21: − Оборудование стандартное | B21: =-Параметры_объект!$C$19 -> -523852459 | C21: =B21/Параметры_объект!$C$7 -> -0.13086973
A22: − Оборудование импортное ядро 🔴 | B22: =-Параметры_объект!$C$20 -> -1999754098 | C22: =B22/Параметры_объект!$C$7 -> -0.49958205
A23: − СМР (работы+монтаж+ПНР+перевозки) | B23: =-Параметры_объект!$C$21 -> -277868852 | C23: =B23/Параметры_объект!$C$7 -> -0.06941768
A24: ИТОГО ВАЛОВАЯ МАРЖА (GM1) | B24: =B19+B20+B21+B22+B23 -> 3.0160178e+08 | C24: =B24/Параметры_объект!$C$7 -> 0.075346683
A25: − Косвенные генподряда за срок | B25: =-B13 -> -236196200 | C25: =B25/Параметры_объект!$C$7 -> -0.059006946
A26: − ОПР/ОХР холдинга (2%) | B26: =-B19*Параметры_объект!$C$13 -> -65620560 | C26: =B26/Параметры_объект!$C$7 -> -0.016393443
A27: − Стоимость ГУ 5% (заморозка ~0,8 года) | B27: =-Параметры_объект!$C$7/(1+Параметры_объект!$C$8)*Параметры_объект!$C$11*Параметры_объект!$C$14*0.8 -> -26248224 | C27: =B27/Параметры_объект!$C$7 -> -0.006557377
A28: − Стоимость кассовых разрывов ⚠ | B28: -16306797 | C28: =B28/Параметры_объект!$C$7 -> -0.0040737924
A29: ИТОГО EBT (прибыль до налога) | B29: =B24+B25+B26+B27+B28 -> -42769996 | C29: =B29/Параметры_объект!$C$7 -> -0.010684875
A31: Проверка: EBT базы Йошкар-Олы ≈ −42,8 млн ₽ (−1,1% НМЦК). Плюс появляется только из рычагов (лист «6» ниже / Карта рычагов в записке).
A33: C. КАРТА РЫЧАГОВ — водопад от базового EBT (эффект каждого в ₽)
A34: Рычаг | B34: Эффект, ₽ | C34: Основание | D34: Статус
A35: Базовый EBT (36 мес, до рычагов) | B35: =B29 -> -42769996 | C35: исходная точка
A36: Импортное ядро −10% (КП/импортозамещение) | B36: 244000000 | C36: ст.710 ГК + ПТР | D36: 🔴 КП нет
A37: Коллизии 1–9 → ДС по ст. 95 44-ФЗ | B37: 60300000 | C37: ст.95, лимит +10% | D37: 🟡 согласие заказчика
A38: Сжатие срока 36→30 мес (−косвенные) | B38: 39000000 | C38: СНиП 1.04.03-85* | D38: 🟡 переговоры
A39: Замена ГУ 5% на банковскую гарантию | B39: 30000000 | C39: ст.96 ч.30 44-ФЗ | D39: 🟢 право
A40: СМР: доп. дисконт (свои силы, торг) | B40: 30000000 | C40: сверх +70 млн | D40: 🟡 торг
A41: Снижение кассовых разрывов (аванс+b2b) | B41: 10000000 | C41: финдисциплина | D41: 🟢
A42: ИТОГО EBT ПОСЛЕ РЫЧАГОВ (оптимум) | B42: =SUM(B35:B41) -> 3.7053e+08 | C42: ≈ 9,3% НМЦК | D42: 🎯
A43: ЧЕСТНЫЙ ПОТОЛОК: цель «25% с НМЦК» (≈1,0 млрд) легально недостижима. Реалистичный оптимум +370 млн (9,3%). Не приукрашивать.

Sheet 7_Алгоритмы
A1: 7 · АЛГОРИТМЫ ДВИЖКА (формулы — применимы и в режиме [БЕЗ БАЗЫ])
A3: ФОТ по роли | B3: ставка/день = оклад_мес ÷ 30; с налогами = ×1,44 (оклад) / ×1,2 (сдельные); ФОТ = ставка × кол-во × дней; дни ИТР = произв.×1,3
A4: Сроки / бригады | B4: дни = объём ÷ (выработка × бригада). Нормативный срок — пересчёт по СНиП 1.04.03-85* (интерполяция) как независимая опора
A5: Себестоимость → EBT | B5: прямые (мат+оборуд.станд+ЯДРО+СМР+ПНР+перевозки) → GM1 − косвенные за срок − ОПР/ОХР − стоимость денег (ГУ/БГ/разрывы) = EBT. Налог отдельным слоем
A6: Сведение цены 44-ФЗ | B6: база ФСНБ-2022 → ×индекс факт. инфляции → ×индекс прогнозной (бленд по годам) → +непредвид.2% → ×доведение до лимита → ×(1+НДС) = НМЦК. Эталон совокупно ×1,629
A7: Стоимость ГУ | B7: Стоимость ГУ = сумма ГУ × ставка капитала × срок заморозки. Замена на БГ: экономия = стоимость ГУ − (сумма × 1,5%/год × срок)
A8: Эффект концентрации | B8: найти ядро (топ-20). Каждые −5% цены ядра = ядро×0,05 к EBT (эталон: 2,44 млрд ×5% ≈ +122 млн)
A9: Коэф. рыночности СМР | B9: дельта = НМЦК_группы × (1 − коэф); коэф 0,80–0,92 по группам работ (лист 1)
A10: Деньги во времени | B10: аванс гасится с каждого КС; казначейское сопровождение → БДДС по годам; пеня = сумма × (1/300 × ключевая ставка) в ₽/день

Sheet 8_Нормбаза
A1: 8 · НОРМБАЗА — документ → статус «действует / отменён» → актуальный аналог (проверять на дату!)
A3: Документ | B3: Статус | C3: Актуальный аналог / примечание | D3: Область
A4: РД-11-02-2006 | B4: ❌ отменён | C4: Приказ Минстроя № 344/пр (ред. 23.06.2025) | D4: ИД, АОСР
A5: РД-11-05-2007 | B5: ❌ отменён | C5: ОЖР — Приказ № 1026/пр | D5: журнал работ
A6: ПП 815 | B6: ❌ отменено с 01.09.2024 | C6: проверить актуальный механизм обязательности СП | D6: обяз. перечни
A7: СП 5.13130.2009 | B7: ❌ отменён | C7: СП 484/485/486.1311500.2020 | D7: АУПС/АУПТ
A8: СНиП 3.05.03-85 | B8: ❌ устарел | C8: СП 74.13330.2023 | D8: теплосети
A9: СНиП 21-01-97* | B9: ❌ отменён | C9: ФЗ-123 + СП 2.13130.2020 | D9: пожарная
A10: СНиП 1.04.03-85* | B10: ⚠ применяется как опора | C10: пересчёт нормативного срока строительства (интерполяция) | D10: сроки
A11: СП 34.13330 | B11: ✅ проверить ред. | C11: автомобильные дороги | D11: дороги
A12: СП 78.13330 | B12: ✅ проверить ред. | C12: производство работ по дорогам | D12: дороги
A13: ГОСТ Р 58406.x | B13: ✅ проверить ред. | C13: асфальтобетонные смеси | D13: дороги
A14: СП 32.13330 / 31.13330 | B14: ✅ проверить ред. | C14: канализация / водоснабжение | D14: ВКХ
... A18: ГК РФ ст.709/710/716/719/743/741 | B18: ✅ действует | C18: твёрдая цена / экономия / приостановка / объёмы / риск | D18: право

Sheet 9_Реестр_объектов
A1: 9 · РЕЕСТР ОБЪЕКТОВ — провенанс цифр базы
A3: ID | B3: Объект | C3: Домен | D3: НМЦК/сумма | E3: Роль | F3: Год | G3: Что дал базе
A4: SI-2026-ОСК-ЙО | B4: ОСК Йошкар-Ола, 2 этап | C4: ВКХ | D4: 4002854177 | E4: генподряд | F4: 2026 | G4: Косвенные, слои себест., финмодель, коллизии, аналоги, рыночность СМР
A5: (кейс) Каранайаул | B5: Дорога, Дагестан | C5: Дороги | D5: — | E5: генподряд | F5: 2025 | G5: Битум +158% к смете — риск маржи (пример)
A6: (кейс) Школа №19 | B6: Школа, Москва | C6: Общестрой | D6: — | E6: генподряд | F6: 2025 | G6: Кассовый разрыв за 13 мес; ГУ 5%=101 млн (пример)

Sheet 10_Уроки
A1: 10 · УРОКИ — вшиты в стандарт работы агента
A3: Косвенные съедают валовую | B3: На объекте 4 млрд/36 мес валовая 301,6 млн < косвенные 344 млн → база убыточна. Считать косвенные помесячно × срок ВСЕГДА, доводить до EBT
A4: Ядро без КП = иллюзия | B4: 61% бюджета (2,44 млрд) без живого КП — итоговая сумма это коридор, не цифра. КП по топ-6 в первые 10 дней
A5: Коллизии РД↔смета | B5: 9 недоборов = 60,3 млн убытка при твёрдой цене, если не оформить ДС по ст.95. Задвоение (водослив +8,7 млн) — риск ФАС, экономику не строить
A6: Срок в ПОС врёт | B6: Арифм. ошибка ПОС: 32 vs 26 мес по формуле; норматив СНиП ≈30; договор 36 → резерв сжатия +39 млн. Пересчитывать срок независимо
A7: Сходимость сметы | B7: Сумма ЛСР = свод до рубля (урок Каранайаула: ЛСР выпала на 3,5 млн). Разошлось → искать выпавшую позицию, не перекрывать
A8: Синтетическая цена промахивается | B8: Цена «по классу» на тяжёлом оборудовании мимо в 2–11× (Урок-Марина). Тяжёлое/длинноцикл — только под живое КП
A9: Цена гуляет по каналам | B9: Одна позиция: 10–35% между каналами, до 6× между спецификациями (Урок-Канал). Твёрдая цена = поздняя комплектная выборка + КП
A10: Тип заказчика — первым | B10: 44-ФЗ/223 → ГУ/БГ/казначейство/НДС; коммерция → ГК РФ. Определять на Шаге 0 — меняет весь контур
A11: Битум — риск дорог №1 | B11: Волатильность цены битума (кейс +158%) ловить ДО подписания, а не на укладке
A12: РНП-гейт (для МОДЦ) | B12: Компания в РНП не проходит ст.31 44-ФЗ. Проверять допуск ДО оценки тендера, называть прямо

Sheet 11_Сверка_расчёт_факт
A1: 11 · СВЕРКА РАСЧЁТ vs ФАКТ — заполняется по мере прихода живых КП/счетов
A3: Пример-строка ниже показывает формат. Когда приходит КП — вносишь цену B, база пересчитывает Δ. Живой КП всегда бьёт оценку.
A5: Позиция | B5: Ед | C5: Цена A (оценка) | D5: Ист. A | E5: Цена B (факт/КП) | F5: Ист. B | G5: Δ ₽/ед | H5: Δ % | I5: Кол-во
A6: (пример) Насос Р-420 | B6: шт | C6: 46198593 | D6: НМЦК оценка | E6: под КП | F6: ждём КП | G6: =IFERROR(E6-C6,"") | H6: =IFERROR((E6-C6)/C6,"") | I6: 3
G7: =IFERROR(E7-C7,"") -> 0 | H7: =IFERROR((E7-C7)/C7,"")
G8: =IFERROR(E8-C8,"") -> 0 | H8: =IFERROR((E8-C8)/C8,"")
G9: =IFERROR(E9-C9,"") -> 0 | H9: =IFERROR((E9-C9)/C9,"")
G10: =IFERROR(E10-C10,"") -> 0 | H10: =IFERROR((E10-C10)/C10,"")
G11: =IFERROR(E11-C11,"") -> 0 | H11: =IFERROR((E11-C11)/C11,"")
G12: =IFERROR(E12-C12,"") -> 0 | H12: =IFERROR((E12-C12)/C12,"")
G13: =IFERROR(E13-C13,"") -> 0 | H13: =IFERROR((E13-C13)/C13,"")
G14: =IFERROR(E14-C14,"") -> 0 | H14: =IFERROR((E14-C14)/C14,"")

Sheet 12_Поставщики_аналоги
A1: 12 · ПОСТАВЩИКИ И КАРТА ИМПОРТ → РФ-АНАЛОГ (по группам; ⚠ до живых КП)
A3: Группа / позиция | B3: НМЦК, ₽ | C3: Импорт (бренд) | D3: РФ-аналог (производители) | E3: Экономия ₽ | F3: Экон.% | G3: Приор.
A4: Дисковый фильтр 3-й очистки | B4: 785200000 | C4: Alfa Laval | D4: Экополимер, ИнСфера (сито TR) | E4: 78,5–117,8 млн | F4: 10–15% | G4: 🔴1
A5: УФ-станция обеззараживания | B5: 667100000 | C5: импорт | D5: НПО ЛИТ (УДВ), Мелитта, ВОДГЕО | E5: 80,1–120,1 млн | F5: 12–18% | G5: 🔴2
A6: Насосы осевые/погружные (18) | B6: 329400000 | C6: Flygt, BBA | D6: ГМС Ливгидромаш, ЭНА, Гидромашсервис | E6: 32,9–59,3 млн | F6: 10–18% | G6: 🔴3
A7: Затворы/шиберы, ШУ (54) | B7: 254300000 | C7: импорт | D7: Ротор, Экотон, ИнСфера | E7: 25,4–38,1 млн | F7: 10–15% | G7: 🟡4
A8: Отстойники / илоскрёбы | B8: 168800000 | C8: импорт | D8: ИнСфера, Аргель, Техносфера-Центр | E8: 16,9–25,3 млн | F8: 10–15% | G8: 🟡5
A9: Решётки грубой/тонкой очистки (5) | B9: 68100000 | C9: Finnchain | D9: ИнСфера Hydrig RG/RGK/SR (прямой) | E9: 13,6–20,4 млн | F9: 20–30% | G9: 🟡8
A10: Песколовки/скребковые системы | B10: 61000000 | C10: Finnchain | D10: ИнСфера KURP, Экотон (прямой) | E10: 12,2–18,3 млн | F10: 20–30% | G10: 🟡9
A11: Трубы GRP DN1500 (6) | B11: 61000000 | C11: импорт GRP | D11: Стеклопластик Казань (~150 км), Гидрокор | E11: 6,1–9,2 млн | F11: 10–15% | G11: 🟢10
A12: КТП/котельная/воздуходувки+прочее | B12: 693000000 | C12: смеш. | D12: Прямые РФ + ИнСфера комплектно | E12: 39–74 млн | F12: 5–10% | G12: 🔵
A13: ИТОГО ПОТЕНЦИАЛ (замена импорта на РФ) | B13: =SUM(B4:B12) -> 3087900000 | E13: 304–481 млн | G13: 🎯
A15: Легализация: перепроектирование (проектный институт) + согласование + повторная экспертиза 1,5–4 мес → ПТР (ст.710 ГК) → КП РФ + верификация «офис≠производство».

Sheet 13.2_ВКХ_очистные
A1: 13.2 · ДОМЕН ВКХ / ОЧИСТНЫЕ — наполнен фактурой Йошкар-Олы (эталонный домен)
A3: Центр тяжести бюджета | B3: Технологическое ОБОРУДОВАНИЕ 60–87% денег. На ОСК: оборуд. 87% фронта снабжения, импортное ядро 78% оборуд. = 2,44 млрд = 61% НМЦК
A4: Техпроцесс ОСК | B4: приёмная камера → механика (решётки → песколовки → первичные отстойники) → биология (аэротенки → вторичные отстойники) → доочистка (дисковые фильтры) → УФ → обработка осадка (обезвоживание)
A5: Балансы (обязаны сходиться) | B5: приток Q (м³/сут и пиковый м³/ч) → нагрузки БПК/ХПК/взвеш./N/P → выход на НОРМАТИВ (рыбхоз/СанПиН). Классика: насос не бьётся с пиковым расходом
A6: Ловушка: резервирование | B6: N рабочих + резерв. РД даёт 4 ед., смета 3 (коллизии 2–4 ОСК: скребок Finnchain, насос Flygt). Недобор = убыток при твёрдой цене
A7: Ловушка: приёмка по нормативу | B7: Приёмка ТОЛЬКО при достижении норматива очистки. За состав входящих стоков отвечает заказчик → оговорка в договоре (протокол разногласий п.1.4)
A8: Ловушка: длинный лид-тайм | B8: Дисковый фильтр, УФ — 16–24 нед. Решение о замене на РФ-аналог принимать в первые недели: перепроектирование+экспертиза 1,5–4 мес, иначе окно закрыто
A9: Точка безубыточности закупки | B9: Индексы НМЦК покрывают удорожание оборуд. до +33,5%. Реальный импорт +32–45% → выше 33,5% убыток. Каждые −5% цены ядра = +122 млн EBT
A10: Прямой РФ-аналог (мех. очистка) | B10: ИнСфера Hydrig (решётки RG/RGK/SR), сита TR, песколовки KURP — минимальное перепроектирование, пилот не нужен. Дисковый фильтр/УФ — через пилот
A11: Нормбаза домена | B11: СП 32.13330 (канализация), СП 31.13330 (водоснабжение), ИТС НДТ 10-2019 — проверять редакцию на дату
A13: ПРОГНОЗ ИД (объём исполнительной документации по видам работ — эталон ОСК)
A14: Вид работ | B14: Позиций | C14: АОСР | D14: Контроль
A15: Земляные работы / основания | B15: 328 | C15: 73 | D15: опрес. траншей, уплотнение грунта
A16: Свайные работы | B16: 25 | C16: 11 | D16: испытание свай, бетон свай
A17: Бетон / ж-б монолитные | B17: 219 | C17: 90 | D17: бетон + арматура
A18: Металлоконструкции | B18: 181 | C18: 68 | D18: НК сварки, ВИК/УЗК
A19: Антикоррозийная защита | B19: 429 | C19: 132 | D19: адгезия, толщина покрытия
A20: Наружные сети водопровод | B20: 208 | C20: 70 | D20: опрес./промывка, уплотнение засыпки
A21: Автодороги / покрытия | B21: 45 | C21: 24 | D21: ровность, керны/уплотнение
A23: Сводный прогноз ИД ОСК: ≈1 246 АОСР, 103 АООК, 709 актов испытаний, 513 лаб.испытаний. Приказ 344/пр (ИД), 1026/пр (ОЖР).

Sheet 13.1_Дороги_ИССО
A1: 13.1 · ДОМЕН ДОРОГИ И ИССО (каркас под МОДЦ — наполнить дорожным объектом)
A3: Каркас домена: структура готова, наполняется цифрами при первом объекте этого типа. До наполнения — режим [БЕЗ БАЗЫ] по числам.
A5: Центр тяжести бюджета | B5: Материалы и ЛОГИСТИКА: битум/ПБВ, инертные (щебень/песок/ЩПС), а/б смеси, геосинтетика, борт.камень, барьерное огражд., трубы, освещение, знаки. Плечо инертных ₽/т·км — отдельно
A6: Длинноцикл / под КП | B6: Битум/ПБВ (волатильность!), балки моста, опоры, барьерное ограждение; спецтехника (краны большой г/п) с моб/демоб
A7: Ловушка: битум | B7: Кейс Каранайаул +158% к смете — главный риск маржи, ловить ДО подписания. Формульная привязка цены к бирже
A8: Ловушка: сезонное окно | B8: Температурное окно укладки а/б и «мокрых» работ — план от климатического окна региона НАЗАД
A9: Ловушка: гарантия | B9: Колейность, ровность IRI — отложенный убыток в гарантийный период
A10: Свой АБЗ | B10: Смесь считать снизу (битум+инертные+энергия+ФОТ), не по прайсу; загрузка АБЗ и логистика смеси (t укладки) — критический путь
A11: Нормбаза | B11: ГОСТ Р 58406.x (а/б смеси), СП 34.13330 (автодороги), СП 78.13330 (производство работ) — проверять редакцию
A12: Сборники ФЕР | B12: ФЕР-27 дороги, ФЕР-30 мосты

Sheet 13.3_Сети_ИТП
A1: 13.3 · ДОМЕН ИНЖЕНЕРНЫЕ СЕТИ / ИТП (каркас)
A3: Каркас домена: структура готова, наполняется цифрами при первом объекте этого типа. До наполнения — режим [БЕЗ БАЗЫ] по числам.
A5: Центр тяжести | B5: Материалы (трубы, арматура, кабель, изоляция) + тяжёлое оборуд. (БТП, насосные, ПВУ) под КП
A6: Ловушка: цена по классу | B6: Синтетическая цена промахивается до 11× (Урок-Марина). Тяжёлое оборуд. — только под живое КП
A7: Ловушка: каналы | B7: Одна позиция гуляет 10–35% между каналами, до 6× между спецификациями (Урок-Канал). Твёрдая цена = поздняя выборка + КП
A8: Ловушка: охват РД | B8: Нет раздела = «вне охвата», не угадывать. Неполный охват занижает бюджет кратно
A9: Гидравлика | B9: Диаметры — двойной сверкой: скорость v И удельные потери R (СП 124.13330)
A10: РФ-аналоги | B10: Danfoss→Ридан; Grundfos/Wilo→ANTARUS; Buderus→отеч. панельные; кабель — Камкабель/Кабэкс

Sheet 13.4_Промонтаж
A1: 13.4 · ДОМЕН ПРОМЫШЛЕННЫЙ МОНТАЖ (каркас)
A3: Каркас домена: структура готова, наполняется цифрами при первом объекте этого типа. До наполнения — режим [БЕЗ БАЗЫ] по числам.
A5: Центр тяжести | B5: Труд и его производные (высокая доля ФОТ). Вахта съедает маржу
A6: НАКС + электрод под марку | B6: 09Г2С→УОНИ13/55; аустенит→ОК61.85; 12ХМ→ОК76.18; ASME SA-537→ОК74.70. Подмена электрода = брак на ОПО
A7: Объёмная т/о (PWHT) | B7: Cr-Mo (12ХМ) и толстостенные/ASME — обязательна (услуги ~600–800к + изоляция + топливо)
A8: Толщина/положение | B8: 33→52 мм: электроды ×2,56; проектное положение ≈×1,45 к горизонту
A9: Корпоративная расценка | B9: КОЕРр и аналоги — не ФЕР, проверять норматив внутри; давальческие — поимённо
A10: Вахта | B10: Суточные 600–700, проживание 500–1500, билет ДВ до 15к, аттестация НАКС до 650к пулом — снизу вверх

Sheet 13.5_Общестрой_КЖ
A1: 13.5 · ДОМЕН ОБЩЕСТРОЙ / КЖ / СОЦИАЛЬНЫЕ (каркас)
A3: Каркас домена: структура готова, наполняется цифрами при первом объекте этого типа. До наполнения — режим [БЕЗ БАЗЫ] по числам.
A5: Центр тяжести | B5: КЖ (бетон/арматура) + фасады/кровля + внутренние сети + отделка
A6: Длинноцикл | B6: Витражи, лифты, вентоборудование — 12–16 нед
A7: Ловушка: 1 компл. | B7: «1 компл.» в смете без расшифровки ≥5% НМЦК = блокер, расшифровка через заказчика
A8: Ловушка: кассовый разрыв | B8: Длинные социальные контракты — эталон Школа №19: разрыв за 13 мес, ГУ 5% = 101 млн вне оборота

Sheet 13.6_Энергетика
A1: 13.6 · ДОМЕН ЭНЕРГЕТИКА / ЭЛЕКТРОСЕТИ (каркас)
A3: Каркас домена: структура готова, наполняется цифрами при первом объекте этого типа. До наполнения — режим [БЕЗ БАЗЫ] по числам.
A5: Центр тяжести | B5: КТП/РУ/трансформаторы + кабель (медь — биржевая волатильность)
A6: Ловушка: техприсоединение | B6: Границы балансовой принадлежности, сроки ТП
A7: Ловушка: ПУЭ | B7: Подмена меди на алюминий — только по проекту (ГИП+ПТР)
A8: ИД | B8: Электролаборатория / ПСИ в объёме ИД обязательны

Sheet 13.7_Благоустройство
A1: 13.7 · ДОМЕН БЛАГОУСТРОЙСТВО (каркас)
A3: Каркас домена: структура готова, наполняется цифрами при первом объекте этого типа. До наполнения — режим [БЕЗ БАЗЫ] по числам.
A5: Центр тяжести | B5: Плитка/камень/МАФ/озеленение
A6: Ловушка: сезон | B6: Окно посадок и «мокрых» работ
A7: Ловушка: приёмка по эстетике | B7: Субъективная — фиксировать критерии в договоре
A8: Ловушка: гарантия | B8: Вандализм в гарантийный период
